Workbook
Name filtered_headers: _xlfn._xlws.FILTER(netflixPart2!XEZ1:A1,ISNA(_xlfn.XMATCH(netflixPart2!XEZ1:A1,netflixPart1!XEZ1:XFD1)))

Sheet netflixPart2
A1: show_id | B1: date_added | C1: release_year | D1: rating | E1: duration | F1: listed_in
A2: s1 | B2: 9/25/2021 | C2: 2020 | D2: PG-13 | E2: 90 min | F2: Documentaries
A3: s3 | B3: 9/24/2021 | C3: 2021 | D3: TV-MA | E3: 1 Season | F3: Crime TV Shows, International TV Shows, TV Action & Adventure
A4: s6 | B4: 9/24/2021 | C4: 2021 | D4: TV-MA | E4: 1 Season | F4: TV Dramas, TV Horror, TV Mysteries
A5: s14 | B5: 9/22/2021 | C5: 2021 | D5: TV-PG | E5: 91 min | F5: Children & Family Movies, Comedies
A6: s8 | B6: 9/24/2021 | C6: 1993 | D6: TV-MA | E6: 125 min | F6: Dramas, Independent Movies, International Movies
A7: s9 | B7: 9/24/2021 | C7: 2021 | D7: TV-14 | E7: 9 Seasons | F7: British TV Shows, Reality TV
A8: s10 | B8: 9/24/2021 | C8: 2021 | D8: PG-13 | E8: 104 min | F8: Comedies, Dramas
A9: s939 | B9: 05/01/2021 | C9: 2019 | D9: TV-Y7 | E9: 87 min | F9: Children & Family Movies, Comedies, Music & Musicals
A10: s13 | B10: 9/23/2021 | C10: 2021 | D10: TV-MA | E10: 127 min | F10: Dramas, International Movies
A11: s940 | B11: 05/01/2021 | C11: 2013 | D11: TV-Y7 | E11: 76 min | F11: Children & Family Movies, Music & Musicals
A12: s941 | B12: 05/01/2021 | C12: 2014 | D12: TV-Y7 | E12: 76 min | F12: Children & Family Movies, Comedies
A13: s942 | B13: 05/01/2021 | C13: 2013 | D13: TV-Y7 | E13: 71 min | F13: Children & Family Movies, Comedies
... A8791: s8786 | B8791: 06/07/2018 | C8791: 2016 | D8791: TV-Y7 | E8791: 1 Season | F8791: Kids' TV

Sheet netflixPart1
A1: show_id | B1: type | C1: title | D1: director | E1: country | F1: {=_xlfn._xlws.FILTER(netflixPart2!A1:F1,ISNA(_xlfn.XMATCH(netflixPart2!A1:F1,A1:E1)))} -> date_added | G1: release_year | H1: rating | I1: duration | J1: listed_in | K1: duplication
A2: s1 | B2: Movie | C2: Dick Johnson Is Dead | D2: Kirsten Johnson | E2: United States | F2: {=IFERROR(_xlfn.XLOOKUP($A2,netflixPart2!$A:$A,_xlfn.CHOOSECOLS(netflixPart2!$A:$F,_xlfn.XMATCH(netflixPart1!F$1,netflixPart2!$A$1:$F$1))),"Missing")} -> 9/25/2021 | G2: {=DATE(IFERROR(_xlfn.XLOOKUP($A2,netflixPart2!$A:$A,_xlfn.CHOOSECOLS(netflixPart2!$A:$F,_xlfn.XMATCH(netflixPart1!G$1,netflixPart2!$A$1:$F$1))),"Missing"),1,1)} -> 43831 | H2: {=IFERROR(_xlfn.XLOOKUP($A2,netflixPart2!$A:$A,_xlfn.CHOOSECOLS(netflixPart2!$A:$F,_xlfn.XMATCH(netflixPart1!H$1,netflixPart2!$A$1:$F$1))),"Missing")} -> PG-13 | I2: {=IFERROR(_xlfn.XLOOKUP($A2,netflixPart2!$A:$A,_xlfn.CHOOSECOLS(netflixPart2!$A:$F,_xlfn.XMATCH(netflixPart1!I$1,netflixPart2!$A$1:$F$1))),"Missing")} -> 90 min | J2: {=IFERROR(_xlfn.XLOOKUP($A2,netflixPart2!$A:$A,_xlfn.CHOOSECOLS(netflixPart2!$A:$F,_xlfn.XMATCH(netflixPart1!J$1,netflixPart2!$A$1:$F$1))),"Missing")} -> Documentaries
A3: s3 | B3: TV Show | C3: Ganglands | D3: Julien Leclercq | E3: France | F3: {=IFERROR(_xlfn.XLOOKUP($A3,netflixPart2!$A:$A,_xlfn.CHOOSECOLS(netflixPart2!$A:$F,_xlfn.XMATCH(netflixPart1!F$1,netflixPart2!$A$1:$F$1))),"Missing")} -> 9/24/2021 | G3: {=DATE(IFERROR(_xlfn.XLOOKUP($A3,netflixPart2!$A:$A,_xlfn.CHOOSECOLS(netflixPart2!$A:$F,_xlfn.XMATCH(netflixPart1!G$1,netflixPart2!$A$1:$F$1))),"Missing"),1,1)} -> 44197 | H3: {=IFERROR(_xlfn.XLOOKUP($A3,netflixPart2!$A:$A,_xlfn.CHOOSECOLS(netflixPart2!$A:$F,_xlfn.XMATCH(netflixPart1!H$1,netflixPart2!$A$1:$F$1))),"Missing")} -> TV-MA | I3: {=IFERROR(_xlfn.XLOOKUP($A3,netflixPart2!$A:$A,_xlfn.CHOOSECOLS(netflixPart2!$A:$F,_xlfn.XMATCH(netflixPart1!I$1,netflixPart2!$A$1:$F$1))),"Missing")} -> 1 Season | J3: {=IFERROR(_xlfn.XLOOKUP($A3,netflixPart2!$A:$A,_xlfn.CHOOSECOLS(netflixPart2!$A:$F,_xlfn.XMATCH(netflixPart1!J$1,netflixPart2!$A$1:$F$1))),"Missing")} -> Crime TV Shows, International TV Shows, TV Action & Adventure
A4: s6 | B4: TV Show | C4: Midnight Mass | D4: Mike Flanagan | E4: United States | F4: {=IFERROR(_xlfn.XLOOKUP($A4,netflixPart2!$A:$A,_xlfn.CHOOSECOLS(netflixPart2!$A:$F,_xlfn.XMATCH(netflixPart1!F$1,netflixPart2!$A$1:$F$1))),"Missing")} -> 9/24/2021 | G4: {=DATE(IFERROR(_xlfn.XLOOKUP($A4,netflixPart2!$A:$A,_xlfn.CHOOSECOLS(netflixPart2!$A:$F,_xlfn.XMATCH(netflixPart1!G$1,netflixPart2!$A$1:$F$1))),"Missing"),1,1)} -> 44197 | H4: {=IFERROR(_xlfn.XLOOKUP($A4,netflixPart2!$A:$A,_xlfn.CHOOSECOLS(netflixPart2!$A:$F,_xlfn.XMATCH(netflixPart1!H$1,netflixPart2!$A$1:$F$1))),"Missing")} -> TV-MA | I4: {=IFERROR(_xlfn.XLOOKUP($A4,netflixPart2!$A:$A,_xlfn.CHOOSECOLS(netflixPart2!$A:$F,_xlfn.XMATCH(netflixPart1!I$1,netflixPart2!$A$1:$F$1))),"Missing")} -> 1 Season | J4: {=IFERROR(_xlfn.XLOOKUP($A4,netflixPart2!$A:$A,_xlfn.CHOOSECOLS(netflixPart2!$A:$F,_xlfn.XMATCH(netflixPart1!J$1,netflixPart2!$A$1:$F$1))),"Missing")} -> TV Dramas, TV Horror, TV Mysteries
A5: s14 | B5: Movie | C5: Confessions of an Invisible Girl | D5: Bruno Garotti | E5: Brazil | F5: {=IFERROR(_xlfn.XLOOKUP($A5,netflixPart2!$A:$A,_xlfn.CHOOSECOLS(netflixPart2!$A:$F,_xlfn.XMATCH(netflixPart1!F$1,netflixPart2!$A$1:$F$1))),"Missing")} -> 9/22/2021 | G5: {=DATE(IFERROR(_xlfn.XLOOKUP($A5,netflixPart2!$A:$A,_xlfn.CHOOSECOLS(netflixPart2!$A:$F,_xlfn.XMATCH(netflixPart1!G$1,netflixPart2!$A$1:$F$1))),"Missing"),1,1)} -> 44197 | H5: {=IFERROR(_xlfn.XLOOKUP($A5,netflixPart2!$A:$A,_xlfn.CHOOSECOLS(netflixPart2!$A:$F,_xlfn.XMATCH(netflixPart1!H$1,netflixPart2!$A$1:$F$1))),"Missing")} -> TV-PG | I5: {=IFERROR(_xlfn.XLOOKUP($A5,netflixPart2!$A:$A,_xlfn.CHOOSECOLS(netflixPart2!$A:$F,_xlfn.XMATCH(netflixPart1!I$1,netflixPart2!$A$1:$F$1))),"Missing")} -> 91 min | J5: {=IFERROR(_xlfn.XLOOKUP($A5,netflixPart2!$A:$A,_xlfn.CHOOSECOLS(netflixPart2!$A:$F,_xlfn.XMATCH(netflixPart1!J$1,netflixPart2!$A$1:$F$1))),"Missing")} -> Children & Family Movies, Comedies
A6: s8 | B6: Movie | C6: Sankofa | D6: Haile Gerima | E6: United States | F6: {=IFERROR(_xlfn.XLOOKUP($A6,netflixPart2!$A:$A,_xlfn.CHOOSECOLS(netflixPart2!$A:$F,_xlfn.XMATCH(netflixPart1!F$1,netflixPart2!$A$1:$F$1))),"Missing")} -> 9/24/2021 | G6: {=DATE(IFERROR(_xlfn.XLOOKUP($A6,netflixPart2!$A:$A,_xlfn.CHOOSECOLS(netflixPart2!$A:$F,_xlfn.XMATCH(netflixPart1!G$1,netflixPart2!$A$1:$F$1))),"Missing"),1,1)} -> 33970 | H6: {=IFERROR(_xlfn.XLOOKUP($A6,netflixPart2!$A:$A,_xlfn.CHOOSECOLS(netflixPart2!$A:$F,_xlfn.XMATCH(netflixPart1!H$1,netflixPart2!$A$1:$F$1))),"Missing")} -> TV-MA | I6: {=IFERROR(_xlfn.XLOOKUP($A6,netflixPart2!$A:$A,_xlfn.CHOOSECOLS(netflixPart2!$A:$F,_xlfn.XMATCH(netflixPart1!I$1,netflixPart2!$A$1:$F$1))),"Missing")} -> 125 min | J6: {=IFERROR(_xlfn.XLOOKUP($A6,netflixPart2!$A:$A,_xlfn.CHOOSECOLS(netflixPart2!$A:$F,_xlfn.XMATCH(netflixPart1!J$1,netflixPart2!$A$1:$F$1))),"Missing")} -> Dramas, Independent Movies, International Movies
A7: s9 | B7: TV Show | C7: The Great British Baking Show | D7: Andy Devonshire | E7: United Kingdom | F7: {=IFERROR(_xlfn.XLOOKUP($A7,netflixPart2!$A:$A,_xlfn.CHOOSECOLS(netflixPart2!$A:$F,_xlfn.XMATCH(netflixPart1!F$1,netflixPart2!$A$1:$F$1))),"Missing")} -> 9/24/2021 | G7: {=DATE(IFERROR(_xlfn.XLOOKUP($A7,netflixPart2!$A:$A,_xlfn.CHOOSECOLS(netflixPart2!$A:$F,_xlfn.XMATCH(netflixPart1!G$1,netflixPart2!$A$1:$F$1))),"Missing"),1,1)} -> 44197 | H7: {=IFERROR(_xlfn.XLOOKUP($A7,netflixPart2!$A:$A,_xlfn.CHOOSECOLS(netflixPart2!$A:$F,_xlfn.XMATCH(netflixPart1!H$1,netflixPart2!$A$1:$F$1))),"Missing")} -> TV-14 | I7: {=IFERROR(_xlfn.XLOOKUP($A7,netflixPart2!$A:$A,_xlfn.CHOOSECOLS(netflixPart2!$A:$F,_xlfn.XMATCH(netflixPart1!I$1,netflixPart2!$A$1:$F$1))),"Missing")} -> 9 Seasons | J7: {=IFERROR(_xlfn.XLOOKUP($A7,netflixPart2!$A:$A,_xlfn.CHOOSECOLS(netflixPart2!$A:$F,_xlfn.XMATCH(netflixPart1!J$1,netflixPart2!$A$1:$F$1))),"Missing")} -> British TV Shows, Reality TV
A8: s10 | B8: Movie | C8: The Starling | D8: Theodore Melfi | E8: United States | F8: {=IFERROR(_xlfn.XLOOKUP($A8,netflixPart2!$A:$A,_xlfn.CHOOSECOLS(netflixPart2!$A:$F,_xlfn.XMATCH(netflixPart1!F$1,netflixPart2!$A$1:$F$1))),"Missing")} -> 9/24/2021 | G8: {=DATE(IFERROR(_xlfn.XLOOKUP($A8,netflixPart2!$A:$A,_xlfn.CHOOSECOLS(netflixPart2!$A:$F,_xlfn.XMATCH(netflixPart1!G$1,netflixPart2!$A$1:$F$1))),"Missing"),1,1)} -> 44197 | H8: {=IFERROR(_xlfn.XLOOKUP($A8,netflixPart2!$A:$A,_xlfn.CHOOSECOLS(netflixPart2!$A:$F,_xlfn.XMATCH(netflixPart1!H$1,netflixPart2!$A$1:$F$1))),"Missing")} -> PG-13 | I8: {=IFERROR(_xlfn.XLOOKUP($A8,netflixPart2!$A:$A,_xlfn.CHOOSECOLS(netflixPart2!$A:$F,_xlfn.XMATCH(netflixPart1!I$1,netflixPart2!$A$1:$F$1))),"Missing")} -> 104 min | J8: {=IFERROR(_xlfn.XLOOKUP($A8,netflixPart2!$A:$A,_xlfn.CHOOSECOLS(netflixPart2!$A:$F,_xlfn.XMATCH(netflixPart1!J$1,netflixPart2!$A$1:$F$1))),"Missing")} -> Comedies, Dramas
A9: s939 | B9: Movie | C9: Motu Patlu in the Game of Zones | D9: Suhas Kadav | E9: India | F9: {=IFERROR(_xlfn.XLOOKUP($A9,netflixPart2!$A:$A,_xlfn.CHOOSECOLS(netflixPart2!$A:$F,_xlfn.XMATCH(netflixPart1!F$1,netflixPart2!$A$1:$F$1))),"Missing")} -> 05/01/2021 | G9: {=DATE(IFERROR(_xlfn.XLOOKUP($A9,netflixPart2!$A:$A,_xlfn.CHOOSECOLS(netflixPart2!$A:$F,_xlfn.XMATCH(netflixPart1!G$1,netflixPart2!$A$1:$F$1))),"Missing"),1,1)} -> 43466 | H9: {=IFERROR(_xlfn.XLOOKUP($A9,netflixPart2!$A:$A,_xlfn.CHOOSECOLS(netflixPart2!$A:$F,_xlfn.XMATCH(netflixPart1!H$1,netflixPart2!$A$1:$F$1))),"Missing")} -> TV-Y7 | I9: {=IFERROR(_xlfn.XLOOKUP($A9,netflixPart2!$A:$A,_xlfn.CHOOSECOLS(netflixPart2!$A:$F,_xlfn.XMATCH(netflixPart1!I$1,netflixPart2!$A$1:$F$1))),"Missing")} -> 87 min | J9: {=IFERROR(_xlfn.XLOOKUP($A9,netflixPart2!$A:$A,_xlfn.CHOOSECOLS(netflixPart2!$A:$F,_xlfn.XMATCH(netflixPart1!J$1,netflixPart2!$A$1:$F$1))),"Missing")} -> Children & Family Movies, Comedies, Music & Musicals
A10: s13 | B10: Movie | C10: Je Suis Karl | D10: Christian Schwochow | E10: Germany | F10: {=IFERROR(_xlfn.XLOOKUP($A10,netflixPart2!$A:$A,_xlfn.CHOOSECOLS(netflixPart2!$A:$F,_xlfn.XMATCH(netflixPart1!F$1,netflixPart2!$A$1:$F$1))),"Missing")} -> 9/23/2021 | G10: {=DATE(IFERROR(_xlfn.XLOOKUP($A10,netflixPart2!$A:$A,_xlfn.CHOOSECOLS(netflixPart2!$A:$F,_xlfn.XMATCH(netflixPart1!G$1,netflixPart2!$A$1:$F$1))),"Missing"),1,1)} -> 44197 | H10: {=IFERROR(_xlfn.XLOOKUP($A10,netflixPart2!$A:$A,_xlfn.CHOOSECOLS(netflixPart2!$A:$F,_xlfn.XMATCH(netflixPart1!H$1,netflixPart2!$A$1:$F$1))),"Missing")} -> TV-MA | I10: {=IFERROR(_xlfn.XLOOKUP($A10,netflixPart2!$A:$A,_xlfn.CHOOSECOLS(netflixPart2!$A:$F,_xlfn.XMATCH(netflixPart1!I$1,netflixPart2!$A$1:$F$1))),"Missing")} -> 127 min | J10: {=IFERROR(_xlfn.XLOOKUP($A10,netflixPart2!$A:$A,_xlfn.CHOOSECOLS(netflixPart2!$A:$F,_xlfn.XMATCH(netflixPart1!J$1,netflixPart2!$A$1:$F$1))),"Missing")} -> Dramas, International Movies
A11: s940 | B11: Movie | C11: Motu Patlu in Wonderland | D11: Suhas Kadav | E11: India | F11: {=IFERROR(_xlfn.XLOOKUP($A11,netflixPart2!$A:$A,_xlfn.CHOOSECOLS(netflixPart2!$A:$F,_xlfn.XMATCH(netflixPart1!F$1,netflixPart2!$A$1:$F$1))),"Missing")} -> 05/01/2021 | G11: {=DATE(IFERROR(_xlfn.XLOOKUP($A11,netflixPart2!$A:$A,_xlfn.CHOOSECOLS(netflixPart2!$A:$F,_xlfn.XMATCH(netflixPart1!G$1,netflixPart2!$A$1:$F$1))),"Missing"),1,1)} -> 41275 | H11: {=IFERROR(_xlfn.XLOOKUP($A11,netflixPart2!$A:$A,_xlfn.CHOOSECOLS(netflixPart2!$A:$F,_xlfn.XMATCH(netflixPart1!H$1,netflixPart2!$A$1:$F$1))),"Missing")} -> TV-Y7 | I11: {=IFERROR(_xlfn.XLOOKUP($A11,netflixPart2!$A:$A,_xlfn.CHOOSECOLS(netflixPart2!$A:$F,_xlfn.XMATCH(netflixPart1!I$1,netflixPart2!$A$1:$F$1))),"Missing")} -> 76 min | J11: {=IFERROR(_xlfn.XLOOKUP($A11,netflixPart2!$A:$A,_xlfn.CHOOSECOLS(netflixPart2!$A:$F,_xlfn.XMATCH(netflixPart1!J$1,netflixPart2!$A$1:$F$1))),"Missing")} -> Children & Family Movies, Music & Musicals
A12: s941 | B12: Movie | C12: Motu Patlu: Deep Sea Adventure | D12: Suhas Kadav | E12: India | F12: {=IFERROR(_xlfn.XLOOKUP($A12,netflixPart2!$A:$A,_xlfn.CHOOSECOLS(netflixPart2!$A:$F,_xlfn.XMATCH(netflixPart1!F$1,netflixPart2!$A$1:$F$1))),"Missing")} -> 05/01/2021 | G12: {=DATE(IFERROR(_xlfn.XLOOKUP($A12,netflixPart2!$A:$A,_xlfn.CHOOSECOLS(netflixPart2!$A:$F,_xlfn.XMATCH(netflixPart1!G$1,netflixPart2!$A$1:$F$1))),"Missing"),1,1)} -> 41640 | H12: {=IFERROR(_xlfn.XLOOKUP($A12,netflixPart2!$A:$A,_xlfn.CHOOSECOLS(netflixPart2!$A:$F,_xlfn.XMATCH(netflixPart1!H$1,netflixPart2!$A$1:$F$1))),"Missing")} -> TV-Y7 | I12: {=IFERROR(_xlfn.XLOOKUP($A12,netflixPart2!$A:$A,_xlfn.CHOOSECOLS(netflixPart2!$A:$F,_xlfn.XMATCH(netflixPart1!I$1,netflixPart2!$A$1:$F$1))),"Missing")} -> 76 min | J12: {=IFERROR(_xlfn.XLOOKUP($A12,netflixPart2!$A:$A,_xlfn.CHOOSECOLS(netflixPart2!$A:$F,_xlfn.XMATCH(netflixPart1!J$1,netflixPart2!$A$1:$F$1))),"Missing")} -> Children & Family Movies, Comedies
A13: s942 | B13: Movie | C13: Motu Patlu: Mission Moon | D13: Suhas Kadav | E13: India | F13: {=IFERROR(_xlfn.XLOOKUP($A13,netflixPart2!$A:$A,_xlfn.CHOOSECOLS(netflixPart2!$A:$F,_xlfn.XMATCH(netflixPart1!F$1,netflixPart2!$A$1:$F$1))),"Missing")} -> 05/01/2021 | G13: {=DATE(IFERROR(_xlfn.XLOOKUP($A13,netflixPart2!$A:$A,_xlfn.CHOOSECOLS(netflixPart2!$A:$F,_xlfn.XMATCH(netflixPart1!G$1,netflixPart2!$A$1:$F$1))),"Missing"),1,1)} -> 41275 | H13: {=IFERROR(_xlfn.XLOOKUP($A13,netflixPart2!$A:$A,_xlfn.CHOOSECOLS(netflixPart2!$A:$F,_xlfn.XMATCH(netflixPart1!H$1,netflixPart2!$A$1:$F$1))),"Missing")} -> TV-Y7 | I13: {=IFERROR(_xlfn.XLOOKUP($A13,netflixPart2!$A:$A,_xlfn.CHOOSECOLS(netflixPart2!$A:$F,_xlfn.XMATCH(netflixPart1!I$1,netflixPart2!$A$1:$F$1))),"Missing")} -> 71 min | J13: {=IFERROR(_xlfn.XLOOKUP($A13,netflixPart2!$A:$A,_xlfn.CHOOSECOLS(netflixPart2!$A:$F,_xlfn.XMATCH(netflixPart1!J$1,netflixPart2!$A$1:$F$1))),"Missing")} -> Children & Family Movies, Comedies
A14: s852 | B14: Movie | C14: 99 Songs (Tamil) | D14: Not Given | E14: Pakistan | F14: {=IFERROR(_xlfn.XLOOKUP($A14,netflixPart2!$A:$A,_xlfn.CHOOSECOLS(netflixPart2!$A:$F,_xlfn.XMATCH(netflixPart1!F$1,netflixPart2!$A$1:$F$1))),"Missing")} -> 5/21/2021 | G14: {=DATE(IFERROR(_xlfn.XLOOKUP($A14,netflixPart2!$A:$A,_xlfn.CHOOSECOLS(netflixPart2!$A:$F,_xlfn.XMATCH(netflixPart1!G$1,netflixPart2!$A$1:$F$1))),"Missing"),1,1)} -> 44197 | H14: {=IFERROR(_xlfn.XLOOKUP($A14,netflixPart2!$A:$A,_xlfn.CHOOSECOLS(netflixPart2!$A:$F,_xlfn.XMATCH(netflixPart1!H$1,netflixPart2!$A$1:$F$1))),"Missing")} -> TV-14 | I14: {=IFERROR(_xlfn.XLOOKUP($A14,netflixPart2!$A:$A,_xlfn.CHOOSECOLS(netflixPart2!$A:$F,_xlfn.XMATCH(netflixPart1!I$1,netflixPart2!$A$1:$F$1))),"Missing")} -> 131 min | J14: {=IFERROR(_xlfn.XLOOKUP($A14,netflixPart2!$A:$A,_xlfn.CHOOSECOLS(netflixPart2!$A:$F,_xlfn.XMATCH(netflixPart1!J$1,netflixPart2!$A$1:$F$1))),"Missing")} -> Dramas, International Movies, Music & Musicals
A15: s471 | B15: Movie | C15: Bridgerton - The Afterparty | D15: Krysia Plonka, Kristian Mercado | E15: United States | F15: {=IFERROR(_xlfn.XLOOKUP($A15,netflixPart2!$A:$A,_xlfn.CHOOSECOLS(netflixPart2!$A:$F,_xlfn.XMATCH(netflixPart1!F$1,netflixPart2!$A$1:$F$1))),"Missing")} -> 7/13/2021 | G15: {=DATE(IFERROR(_xlfn.XLOOKUP($A15,netflixPart2!$A:$A,_xlfn.CHOOSECOLS(netflixPart2!$A:$F,_xlfn.XMATCH(netflixPart1!G$1,netflixPart2!$A$1:$F$1))),"Missing"),1,1)} -> 44197 | H15: {=IFERROR(_xlfn.XLOOKUP($A15,netflixPart2!$A:$A,_xlfn.CHOOSECOLS(netflixPart2!$A:$F,_xlfn.XMATCH(netflixPart1!H$1,netflixPart2!$A$1:$F$1))),"Missing")} -> TV-14 | I15: {=IFERROR(_xlfn.XLOOKUP($A15,netflixPart2!$A:$A,_xlfn.CHOOSECOLS(netflixPart2!$A:$F,_xlfn.XMATCH(netflixPart1!I$1,netflixPart2!$A$1:$F$1))),"Missing")} -> 39 min | J15: {=IFERROR(_xlfn.XLOOKUP($A15,netflixPart2!$A:$A,_xlfn.CHOOSECOLS(netflixPart2!$A:$F,_xlfn.XMATCH(netflixPart1!J$1,netflixPart2!$A$1:$F$1))),"Missing")} -> Movies | P15: =DATE(1900,1,1) -> 1
A16: s730 | B16: Movie | C16: Bling Empire - The Afterparty | D16: Krysia Plonka, Kristian Mercado | E16: United States | F16: {=IFERROR(_xlfn.XLOOKUP($A16,netflixPart2!$A:$A,_xlfn.CHOOSECOLS(netflixPart2!$A:$F,_xlfn.XMATCH(netflixPart1!F$1,netflixPart2!$A$1:$F$1))),"Missing")} -> 06/12/2021 | G16: {=DATE(IFERROR(_xlfn.XLOOKUP($A16,netflixPart2!$A:$A,_xlfn.CHOOSECOLS(netflixPart2!$A:$F,_xlfn.XMATCH(netflixPart1!G$1,netflixPart2!$A$1:$F$1))),"Missing"),1,1)} -> 44197 | H16: {=IFERROR(_xlfn.XLOOKUP($A16,netflixPart2!$A:$A,_xlfn.CHOOSECOLS(netflixPart2!$A:$F,_xlfn.XMATCH(netflixPart1!H$1,netflixPart2!$A$1:$F$1))),"Missing")} -> TV-MA | I16: {=IFERROR(_xlfn.XLOOKUP($A16,netflixPart2!$A:$A,_xlfn.CHOOSECOLS(netflixPart2!$A:$F,_xlfn.XMATCH(netflixPart1!I$1,netflixPart2!$A$1:$F$1))),"Missing")} -> 36 min | J16: {=IFERROR(_xlfn.XLOOKUP($A16,netflixPart2!$A:$A,_xlfn.CHOOSECOLS(netflixPart2!$A:$F,_xlfn.XMATCH(netflixPart1!J$1,netflixPart2!$A$1:$F$1))),"Missing")} -> Movies
A17: s731 | B17: Movie | C17: Cobra Kai - The Afterparty | D17: Krysia Plonka, Kristian Mercado | E17: United States | F17: {=IFERROR(_xlfn.XLOOKUP($A17,netflixPart2!$A:$A,_xlfn.CHOOSECOLS(netflixPart2!$A:$F,_xlfn.XMATCH(netflixPart1!F$1,netflixPart2!$A$1:$F$1))),"Missing")} -> 06/12/2021 | G17: {=DATE(IFERROR(_xlfn.XLOOKUP($A17,netflixPart2!$A:$A,_xlfn.CHOOSECOLS(netflixPart2!$A:$F,_xlfn.XMATCH(netflixPart1!G$1,netflixPart2!$A$1:$F$1))),"Missing"),1,1)} -> 44197 | H17: {=IFERROR(_xlfn.XLOOKUP($A17,netflixPart2!$A:$A,_xlfn.CHOOSECOLS(netflixPart2!$A:$F,_xlfn.XMATCH(netflixPart1!H$1,netflixPart2!$A$1:$F$1))),"Missing")} -> TV-MA | I17: {=IFERROR(_xlfn.XLOOKUP($A17,netflixPart2!$A:$A,_xlfn.CHOOSECOLS(netflixPart2!$A:$F,_xlfn.XMATCH(netflixPart1!I$1,netflixPart2!$A$1:$F$1))),"Missing")} -> 34 min | J17: {=IFERROR(_xlfn.XLOOKUP($A17,netflixPart2!$A:$A,_xlfn.CHOOSECOLS(netflixPart2!$A:$F,_xlfn.XMATCH(netflixPart1!J$1,netflixPart2!$A$1:$F$1))),"Missing")} -> Movies
A18: s913 | B18: Movie | C18: The Circle - The Afterparty | D18: Krysia Plonka, Kristian Mercado | E18: United States | F18: {=IFERROR(_xlfn.XLOOKUP($A18,netflixPart2!$A:$A,_xlfn.CHOOSECOLS(netflixPart2!$A:$F,_xlfn.XMATCH(netflixPart1!F$1,netflixPart2!$A$1:$F$1))),"Missing")} -> 05/07/2021 | G18: {=DATE(IFERROR(_xlfn.XLOOKUP($A18,netflixPart2!$A:$A,_xlfn.CHOOSECOLS(netflixPart2!$A:$F,_xlfn.XMATCH(netflixPart1!G$1,netflixPart2!$A$1:$F$1))),"Missing"),1,1)} -> 44197 | H18: {=IFERROR(_xlfn.XLOOKUP($A18,netflixPart2!$A:$A,_xlfn.CHOOSECOLS(netflixPart2!$A:$F,_xlfn.XMATCH(netflixPart1!H$1,netflixPart2!$A$1:$F$1))),"Missing")} -> TV-14 | I18: {=IFERROR(_xlfn.XLOOKUP($A18,netflixPart2!$A:$A,_xlfn.CHOOSECOLS(netflixPart2!$A:$F,_xlfn.XMATCH(netflixPart1!I$1,netflixPart2!$A$1:$F$1))),"Missing")} -> 35 min | J18: {=IFERROR(_xlfn.XLOOKUP($A18,netflixPart2!$A:$A,_xlfn.CHOOSECOLS(netflixPart2!$A:$F,_xlfn.XMATCH(netflixPart1!J$1,netflixPart2!$A$1:$F$1))),"Missing")} -> Comedies
A19: s4 | B19: TV Show | C19: Jailbirds New Orleans | D19: Not Given | E19: Pakistan | F19: {=IFERROR(_xlfn.XLOOKUP($A19,netflixPart2!$A:$A,_xlfn.CHOOSECOLS(netflixPart2!$A:$F,_xlfn.XMATCH(netflixPart1!F$1,netflixPart2!$A$1:$F$1))),"Missing")} -> 9/24/2021 | G19: {=DATE(IFERROR(_xlfn.XLOOKUP($A19,netflixPart2!$A:$A,_xlfn.CHOOSECOLS(netflixPart2!$A:$F,_xlfn.XMATCH(netflixPart1!G$1,netflixPart2!$A$1:$F$1))),"Missing"),1,1)} -> 44197 | H19: {=IFERROR(_xlfn.XLOOKUP($A19,netflixPart2!$A:$A,_xlfn.CHOOSECOLS(netflixPart2!$A:$F,_xlfn.XMATCH(netflixPart1!H$1,netflixPart2!$A$1:$F$1))),"Missing")} -> TV-MA | I19: {=IFERROR(_xlfn.XLOOKUP($A19,netflixPart2!$A:$A,_xlfn.CHOOSECOLS(netflixPart2!$A:$F,_xlfn.XMATCH(netflixPart1!I$1,netflixPart2!$A$1:$F$1))),"Missing")} -> 1 Season | J19: {=IFERROR(_xlfn.XLOOKUP($A19,netflixPart2!$A:$A,_xlfn.CHOOSECOLS(netflixPart2!$A:$F,_xlfn.XMATCH(netflixPart1!J$1,netflixPart2!$A$1:$F$1))),"Missing")} -> Docuseries, Reality TV
A20: s15 | B20: TV Show | C20: Crime Stories: India Detectives | D20: Not Given | E20: Pakistan | F20: {=IFERROR(_xlfn.XLOOKUP($A20,netflixPart2!$A:$A,_xlfn.CHOOSECOLS(netflixPart2!$A:$F,_xlfn.XMATCH(netflixPart1!F$1,netflixPart2!$A$1:$F$1))),"Missing")} -> 9/22/2021 | G20: {=DATE(IFERROR(_xlfn.XLOOKUP($A20,netflixPart2!$A:$A,_xlfn.CHOOSECOLS(netflixPart2!$A:$F,_xlfn.XMATCH(netflixPart1!G$1,netflixPart2!$A$1:$F$1))),"Missing"),1,1)} -> 44197 | H20: {=IFERROR(_xlfn.XLOOKUP($A20,netflixPart2!$A:$A,_xlfn.CHOOSECOLS(netflixPart2!$A:$F,_xlfn.XMATCH(netflixPart1!H$1,netflixPart2!$A$1:$F$1))),"Missing")} -> TV-MA | I20: {=IFERROR(_xlfn.XLOOKUP($A20,netflixPart2!$A:$A,_xlfn.CHOOSECOLS(netflixPart2!$A:$F,_xlfn.XMATCH(netflixPart1!I$1,netflixPart2!$A$1:$F$1))),"Missing")} -> 1 Season | J20: {=IFERROR(_xlfn.XLOOKUP($A20,netflixPart2!$A:$A,_xlfn.CHOOSECOLS(netflixPart2!$A:$F,_xlfn.XMATCH(netflixPart1!J$1,netflixPart2!$A$1:$F$1))),"Missing")} -> British TV Shows, Crime TV Shows, Docuseries
A21: s3232 | B21: Movie | C21: True: Winter Wishes | D21: Mark Thornton, Todd Kauffman | E21: United States | F21: {=IFERROR(_xlfn.XLOOKUP($A21,netflixPart2!$A:$A,_xlfn.CHOOSECOLS(netflixPart2!$A:$F,_xlfn.XMATCH(netflixPart1!F$1,netflixPart2!$A$1:$F$1))),"Missing")} -> 11/26/2019 | G21: {=DATE(IFERROR(_xlfn.XLOOKUP($A21,netflixPart2!$A:$A,_xlfn.CHOOSECOLS(netflixPart2!$A:$F,_xlfn.XMATCH(netflixPart1!G$1,netflixPart2!$A$1:$F$1))),"Missing"),1,1)} -> 43466 | H21: {=IFERROR(_xlfn.XLOOKUP($A21,netflixPart2!$A:$A,_xlfn.CHOOSECOLS(netflixPart2!$A:$F,_xlfn.XMATCH(netflixPart1!H$1,netflixPart2!$A$1:$F$1))),"Missing")} -> TV-Y | I21: {=IFERROR(_xlfn.XLOOKUP($A21,netflixPart2!$A:$A,_xlfn.CHOOSECOLS(netflixPart2!$A:$F,_xlfn.XMATCH(netflixPart1!I$1,netflixPart2!$A$1:$F$1))),"Missing")} -> 46 min | J21: {=IFERROR(_xlfn.XLOOKUP($A21,netflixPart2!$A:$A,_xlfn.CHOOSECOLS(netflixPart2!$A:$F,_xlfn.XMATCH(netflixPart1!J$1,netflixPart2!$A$1:$F$1))),"Missing")} -> Children & Family Movies
A22: s4832 | B22: TV Show | C22: True: Magical Friends | D22: Mark Thornton, Todd Kauffman | E22: United States | F22: {=IFERROR(_xlfn.XLOOKUP($A22,netflixPart2!$A:$A,_xlfn.CHOOSECOLS(netflixPart2!$A:$F,_xlfn.XMATCH(netflixPart1!F$1,netflixPart2!$A$1:$F$1))),"Missing")} -> 6/15/2018 | G22: {=DATE(IFERROR(_xlfn.XLOOKUP($A22,netflixPart2!$A:$A,_xlfn.CHOOSECOLS(netflixPart2!$A:$F,_xlfn.XMATCH(netflixPart1!G$1,netflixPart2!$A$1:$F$1))),"Missing"),1,1)} -> 43101 | H22: {=IFERROR(_xlfn.XLOOKUP($A22,netflixPart2!$A:$A,_xlfn.CHOOSECOLS(netflixPart2!$A:$F,_xlfn.XMATCH(netflixPart1!H$1,netflixPart2!$A$1:$F$1))),"Missing")} -> TV-Y | I22: {=IFERROR(_xlfn.XLOOKUP($A22,netflixPart2!$A:$A,_xlfn.CHOOSECOLS(netflixPart2!$A:$F,_xlfn.XMATCH(netflixPart1!I$1,netflixPart2!$A$1:$F$1))),"Missing")} -> 1 Season | J22: {=IFERROR(_xlfn.XLOOKUP($A22,netflixPart2!$A:$A,_xlfn.CHOOSECOLS(netflixPart2!$A:$F,_xlfn.XMATCH(netflixPart1!J$1,netflixPart2!$A$1:$F$1))),"Missing")} -> Kids' TV
A23: s4833 | B23: TV Show | C23: True: Wonderful Wishes | D23: Mark Thornton, Todd Kauffman | E23: United States | F23: {=IFERROR(_xlfn.XLOOKUP($A23,netflixPart2!$A:$A,_xlfn.CHOOSECOLS(netflixPart2!$A:$F,_xlfn.XMATCH(netflixPart1!F$1,netflixPart2!$A$1:$F$1))),"Missing")} -> 6/15/2018 | G23: {=DATE(IFERROR(_xlfn.XLOOKUP($A23,netflixPart2!$A:$A,_xlfn.CHOOSECOLS(netflixPart2!$A:$F,_xlfn.XMATCH(netflixPart1!G$1,netflixPart2!$A$1:$F$1))),"Missing"),1,1)} -> 43101 | H23: {=IFERROR(_xlfn.XLOOKUP($A23,netflixPart2!$A:$A,_xlfn.CHOOSECOLS(netflixPart2!$A:$F,_xlfn.XMATCH(netflixPart1!H$1,netflixPart2!$A$1:$F$1))),"Missing")} -> TV-Y | I23: {=IFERROR(_xlfn.XLOOKUP($A23,netflixPart2!$A:$A,_xlfn.CHOOSECOLS(netflixPart2!$A:$F,_xlfn.XMATCH(netflixPart1!I$1,netflixPart2!$A$1:$F$1))),"Missing")} -> 1 Season | J23: {=IFERROR(_xlfn.XLOOKUP($A23,netflixPart2!$A:$A,_xlfn.CHOOSECOLS(netflixPart2!$A:$F,_xlfn.XMATCH(netflixPart1!J$1,netflixPart2!$A$1:$F$1))),"Missing")} -> Kids' TV
A24: s4857 | B24: TV Show | C24: Dance & Sing with True | D24: Mark Thornton, Todd Kauffman | E24: United States | F24: {=IFERROR(_xlfn.XLOOKUP($A24,netflixPart2!$A:$A,_xlfn.CHOOSECOLS(netflixPart2!$A:$F,_xlfn.XMATCH(netflixPart1!F$1,netflixPart2!$A$1:$F$1))),"Missing")} -> 5/18/2018 | G24: {=DATE(IFERROR(_xlfn.XLOOKUP($A24,netflixPart2!$A:$A,_xlfn.CHOOSECOLS(netflixPart2!$A:$F,_xlfn.XMATCH(netflixPart1!G$1,netflixPart2!$A$1:$F$1))),"Missing"),1,1)} -> 43101 | H24: {=IFERROR(_xlfn.XLOOKUP($A24,netflixPart2!$A:$A,_xlfn.CHOOSECOLS(netflixPart2!$A:$F,_xlfn.XMATCH(netflixPart1!H$1,netflixPart2!$A$1:$F$1))),"Missing")} -> TV-Y | I24: {=IFERROR(_xlfn.XLOOKUP($A24,netflixPart2!$A:$A,_xlfn.CHOOSECOLS(netflixPart2!$A:$F,_xlfn.XMATCH(netflixPart1!I$1,netflixPart2!$A$1:$F$1))),"Missing")} -> 1 Season | J24: {=IFERROR(_xlfn.XLOOKUP($A24,netflixPart2!$A:$A,_xlfn.CHOOSECOLS(netflixPart2!$A:$F,_xlfn.XMATCH(netflixPart1!J$1,netflixPart2!$A$1:$F$1))),"Missing")} -> Kids' TV
A25: s7 | B25: Movie | C25: My Little Pony: A New Generation | D25: Robert Cullen, José Luis Ucha | E25: Not Given | F25: {=IFERROR(_xlfn.XLOOKUP($A25,netflixPart2!$A:$A,_xlfn.CHOOSECOLS(netflixPart2!$A:$F,_xlfn.XMATCH(netflixPart1!F$1,netflixPart2!$A$1:$F$1))),"Missing")} -> 9/24/2021 | G25: {=DATE(IFERROR(_xlfn.XLOOKUP($A25,netflixPart2!$A:$A,_xlfn.CHOOSECOLS(netflixPart2!$A:$F,_xlfn.XMATCH(netflixPart1!G$1,netflixPart2!$A$1:$F$1))),"Missing"),1,1)} -> 44197 | H25: {=IFERROR(_xlfn.XLOOKUP($A25,netflixPart2!$A:$A,_xlfn.CHOOSECOLS(netflixPart2!$A:$F,_xlfn.XMATCH(netflixPart1!H$1,netflixPart2!$A$1:$F$1))),"Missing")} -> PG | I25: {=IFERROR(_xlfn.XLOOKUP($A25,netflixPart2!$A:$A,_xlfn.CHOOSECOLS(netflixPart2!$A:$F,_xlfn.XMATCH(netflixPart1!I$1,netflixPart2!$A$1:$F$1))),"Missing")} -> 91 min | J25: {=IFERROR(_xlfn.XLOOKUP($A25,netflixPart2!$A:$A,_xlfn.CHOOSECOLS(netflixPart2!$A:$F,_xlfn.XMATCH(netflixPart1!J$1,netflixPart2!$A$1:$F$1))),"Missing")} -> Children & Family Movies
A26: s12 | B26: TV Show | C26: Bangkok Breaking | D26: Kongkiat Komesiri | E26: Not Given | F26: {=IFERROR(_xlfn.XLOOKUP($A26,netflixPart2!$A:$A,_xlfn.CHOOSECOLS(netflixPart2!$A:$F,_xlfn.XMATCH(netflixPart1!F$1,netflixPart2!$A$1:$F$1))),"Missing")} -> 9/23/2021 | G26: {=DATE(IFERROR(_xlfn.XLOOKUP($A26,netflixPart2!$A:$A,_xlfn.CHOOSECOLS(netflixPart2!$A:$F,_xlfn.XMATCH(netflixPart1!G$1,netflixPart2!$A$1:$F$1))),"Missing"),1,1)} -> 44197 | H26: {=IFERROR(_xlfn.XLOOKUP($A26,netflixPart2!$A:$A,_xlfn.CHOOSECOLS(netflixPart2!$A:$F,_xlfn.XMATCH(netflixPart1!H$1,netflixPart2!$A$1:$F$1))),"Missing")} -> TV-MA | I26: {=IFERROR(_xlfn.XLOOKUP($A26,netflixPart2!$A:$A,_xlfn.CHOOSECOLS(netflixPart2!$A:$F,_xlfn.XMATCH(netflixPart1!I$1,netflixPart2!$A$1:$F$1))),"Missing")} -> 1 Season | J26: {=IFERROR(_xlfn.XLOOKUP($A26,netflixPart2!$A:$A,_xlfn.CHOOSECOLS(netflixPart2!$A:$F,_xlfn.XMATCH(netflixPart1!J$1,netflixPart2!$A$1:$F$1))),"Missing")} -> Crime TV Shows, International TV Shows, TV Action & Adventure
A27: s17 | B27: Movie | C27: Europe's Most Dangerous Man: Otto Skorzeny in Spain | D27: Pedro de Echave García, Pablo Azorín Williams | E27: Not Given | F27: {=IFERROR(_xlfn.XLOOKUP($A27,netflixPart2!$A:$A,_xlfn.CHOOSECOLS(netflixPart2!$A:$F,_xlfn.XMATCH(netflixPart1!F$1,netflixPart2!$A$1:$F$1))),"Missing")} -> 9/22/2021 | G27: {=DATE(IFERROR(_xlfn.XLOOKUP($A27,netflixPart2!$A:$A,_xlfn.CHOOSECOLS(netflixPart2!$A:$F,_xlfn.XMATCH(netflixPart1!G$1,netflixPart2!$A$1:$F$1))),"Missing"),1,1)} -> 43831 | H27: {=IFERROR(_xlfn.XLOOKUP($A27,netflixPart2!$A:$A,_xlfn.CHOOSECOLS(netflixPart2!$A:$F,_xlfn.XMATCH(netflixPart1!H$1,netflixPart2!$A$1:$F$1))),"Missing")} -> TV-MA | I27: {=IFERROR(_xlfn.XLOOKUP($A27,netflixPart2!$A:$A,_xlfn.CHOOSECOLS(netflixPart2!$A:$F,_xlfn.XMATCH(netflixPart1!I$1,netflixPart2!$A$1:$F$1))),"Missing")} -> 67 min | J27: {=IFERROR(_xlfn.XLOOKUP($A27,netflixPart2!$A:$A,_xlfn.CHOOSECOLS(netflixPart2!$A:$F,_xlfn.XMATCH(netflixPart1!J$1,netflixPart2!$A$1:$F$1))),"Missing")} -> Documentaries, International Movies
... A221: s159 | B221: Movie | C221: Love Don't Cost a Thing | D221: Troy Byer | E221: United States | F221: {=IFERROR(_xlfn.XLOOKUP($A221,netflixPart2!$A:$A,_xlfn.CHOOSECOLS(netflixPart2!$A:$F,_xlfn.XMATCH(netflixPart1!F$1,netflixPart2!$A$1:$F$1))),"Missing")} -> 09/01/2021 | G221: {=DATE(IFERROR(_xlfn.XLOOKUP($A221,netflixPart2!$A:$A,_xlfn.CHOOSECOLS(netflixPart2!$A:$F,_xlfn.XMATCH(netflixPart1!G$1,netflixPart2!$A$1:$F$1))),"Missing"),1,1)} -> 37622 | H221: {=IFERROR(_xlfn.XLOOKUP($A221,netflixPart2!$A:$A,_xlfn.CHOOSECOLS(netflixPart2!$A:$F,_xlfn.XMATCH(netflixPart1!H$1,netflixPart2!$A$1:$F$1))),"Missing")} -> PG-13 | I221: {=IFERROR(_xlfn.XLOOKUP($A221,netflixPart2!$A:$A,_xlfn.CHOOSECOLS(netflixPart2!$A:$F,_xlfn.XMATCH(netflixPart1!I$1,netflixPart2!$A$1:$F$1))),"Missing")} -> 101 min | J221: {=IFERROR(_xlfn.XLOOKUP($A221,netflixPart2!$A:$A,_xlfn.CHOOSECOLS(netflixPart2!$A:$F,_xlfn.XMATCH(netflixPart1!J$1,netflixPart2!$A$1:$F$1))),"Missing")} -> Comedies, Romantic Movies
A222: s160 | B222: Movie | C222: Love in a Puff | D222: Pang Ho-cheung | E222: Hong Kong | F222: {=IFERROR(_xlfn.XLOOKUP($A222,netflixPart2!$A:$A,_xlfn.CHOOSECOLS(netflixPart2!$A:$F,_xlfn.XMATCH(netflixPart1!F$1,netflixPart2!$A$1:$F$1))),"Missing")} -> 09/01/2021 | G222: {=DATE(IFERROR(_xlfn.XLOOKUP($A222,netflixPart2!$A:$A,_xlfn.CHOOSECOLS(netflixPart2!$A:$F,_xlfn.XMATCH(netflixPart1!G$1,netflixPart2!$A$1:$F$1))),"Missing"),1,1)} -> 40179 | H222: {=IFERROR(_xlfn.XLOOKUP($A222,netflixPart2!$A:$A,_xlfn.CHOOSECOLS(netflixPart2!$A:$F,_xlfn.XMATCH(netflixPart1!H$1,netflixPart2!$A$1:$F$1))),"Missing")} -> TV-MA | I222: {=IFERROR(_xlfn.XLOOKUP($A222,netflixPart2!$A:$A,_xlfn.CHOOSECOLS(netflixPart2!$A:$F,_xlfn.XMATCH(netflixPart1!I$1,netflixPart2!$A$1:$F$1))),"Missing")} -> 103 min | J222: {=IFERROR(_xlfn.XLOOKUP($A222,netflixPart2!$A:$A,_xlfn.CHOOSECOLS(netflixPart2!$A:$F,_xlfn.XMATCH(netflixPart1!J$1,netflixPart2!$A$1:$F$1))),"Missing")} -> Comedies, Dramas, International Movies | K222: =_xlfn.TEXTJOIN("|",FALSE,B222:J222) -> Movie|Love in a Puff|Pang Ho-cheung|Hong Kong|09/01/2021|40179|TV-MA|103 min|Comedies, Dramas, International Movies
A223: s1463 | B223: TV Show | C223: Running Man | D223: Not Given | E223: Pakistan | F223: {=IFERROR(_xlfn.XLOOKUP($A223,netflixPart2!$A:$A,_xlfn.CHOOSECOLS(netflixPart2!$A:$F,_xlfn.XMATCH(netflixPart1!F$1,netflixPart2!$A$1:$F$1))),"Missing")} -> 01/01/2021 | G223: {=DATE(IFERROR(_xlfn.XLOOKUP($A223,netflixPart2!$A:$A,_xlfn.CHOOSECOLS(netflixPart2!$A:$F,_xlfn.XMATCH(netflixPart1!G$1,netflixPart2!$A$1:$F$1))),"Missing"),1,1)} -> 43831 | H223: {=IFERROR(_xlfn.XLOOKUP($A223,netflixPart2!$A:$A,_xlfn.CHOOSECOLS(netflixPart2!$A:$F,_xlfn.XMATCH(netflixPart1!H$1,netflixPart2!$A$1:$F$1))),"Missing")} -> TV-Y7 | I223: {=IFERROR(_xlfn.XLOOKUP($A223,netflixPart2!$A:$A,_xlfn.CHOOSECOLS(netflixPart2!$A:$F,_xlfn.XMATCH(netflixPart1!I$1,netflixPart2!$A$1:$F$1))),"Missing")} -> 1 Season | J223: {=IFERROR(_xlfn.XLOOKUP($A223,netflixPart2!$A:$A,_xlfn.CHOOSECOLS(netflixPart2!$A:$F,_xlfn.XMATCH(netflixPart1!J$1,netflixPart2!$A$1:$F$1))),"Missing")} -> Kids' TV, TV Comedies
A224: s162 | B224: Movie | C224: Mars Attacks! | D224: Tim Burton | E224: United States | F224: {=IFERROR(_xlfn.XLOOKUP($A224,netflixPart2!$A:$A,_xlfn.CHOOSECOLS(netflixPart2!$A:$F,_xlfn.XMATCH(netflixPart1!F$1,netflixPart2!$A$1:$F$1))),"Missing")} -> 09/01/2021 | G224: {=DATE(IFERROR(_xlfn.XLOOKUP($A224,netflixPart2!$A:$A,_xlfn.CHOOSECOLS(netflixPart2!$A:$F,_xlfn.XMATCH(netflixPart1!G$1,netflixPart2!$A$1:$F$1))),"Missing"),1,1)} -> 35065 | H224: {=IFERROR(_xlfn.XLOOKUP($A224,netflixPart2!$A:$A,_xlfn.CHOOSECOLS(netflixPart2!$A:$F,_xlfn.XMATCH(netflixPart1!H$1,netflixPart2!$A$1:$F$1))),"Missing")} -> PG-13 | I224: {=IFERROR(_xlfn.XLOOKUP($A224,netflixPart2!$A:$A,_xlfn.CHOOSECOLS(netflixPart2!$A:$F,_xlfn.XMATCH(netflixPart1!I$1,netflixPart2!$A$1:$F$1))),"Missing")} -> 106 min | J224: {=IFERROR(_xlfn.XLOOKUP($A224,netflixPart2!$A:$A,_xlfn.CHOOSECOLS(netflixPart2!$A:$F,_xlfn.XMATCH(netflixPart1!J$1,netflixPart2!$A$1:$F$1))),"Missing")} -> Comedies, Cult Movies, Sci-Fi & Fantasy
A225: s163 | B225: Movie | C225: Marshall | D225: Reginald Hudlin | E225: United States | F225: {=IFERROR(_xlfn.XLOOKUP($A225,netflixPart2!$A:$A,_xlfn.CHOOSECOLS(netflixPart2!$A:$F,_xlfn.XMATCH(netflixPart1!F$1,netflixPart2!$A$1:$F$1))),"Missing")} -> 09/01/2021 | G225: {=DATE(IFERROR(_xlfn.XLOOKUP($A225,netflixPart2!$A:$A,_xlfn.CHOOSECOLS(netflixPart2!$A:$F,_xlfn.XMATCH(netflixPart1!G$1,netflixPart2!$A$1:$F$1))),"Missing"),1,1)} -> 42736 | H225: {=IFERROR(_xlfn.XLOOKUP($A225,netflixPart2!$A:$A,_xlfn.CHOOSECOLS(netflixPart2!$A:$F,_xlfn.XMATCH(netflixPart1!H$1,netflixPart2!$A$1:$F$1))),"Missing")} -> PG-13 | I225: {=IFERROR(_xlfn.XLOOKUP($A225,netflixPart2!$A:$A,_xlfn.CHOOSECOLS(netflixPart2!$A:$F,_xlfn.XMATCH(netflixPart1!I$1,netflixPart2!$A$1:$F$1))),"Missing")} -> 118 min | J225: {=IFERROR(_xlfn.XLOOKUP($A225,netflixPart2!$A:$A,_xlfn.CHOOSECOLS(netflixPart2!$A:$F,_xlfn.XMATCH(netflixPart1!J$1,netflixPart2!$A$1:$F$1))),"Missing")} -> Dramas
A226: s164 | B226: Movie | C226: My Boss's Daughter | D226: David Zucker | E226: United States | F226: {=IFERROR(_xlfn.XLOOKUP($A226,netflixPart2!$A:$A,_xlfn.CHOOSECOLS(netflixPart2!$A:$F,_xlfn.XMATCH(netflixPart1!F$1,netflixPart2!$A$1:$F$1))),"Missing")} -> 09/01/2021 | G226: {=DATE(IFERROR(_xlfn.XLOOKUP($A226,netflixPart2!$A:$A,_xlfn.CHOOSECOLS(netflixPart2!$A:$F,_xlfn.XMATCH(netflixPart1!G$1,netflixPart2!$A$1:$F$1))),"Missing"),1,1)} -> 37622 | H226: {=IFERROR(_xlfn.XLOOKUP($A226,netflixPart2!$A:$A,_xlfn.CHOOSECOLS(netflixPart2!$A:$F,_xlfn.XMATCH(netflixPart1!H$1,netflixPart2!$A$1:$F$1))),"Missing")} -> R | I226: {=IFERROR(_xlfn.XLOOKUP($A226,netflixPart2!$A:$A,_xlfn.CHOOSECOLS(netflixPart2!$A:$F,_xlfn.XMATCH(netflixPart1!I$1,netflixPart2!$A$1:$F$1))),"Missing")} -> 86 min | J226: {=IFERROR(_xlfn.XLOOKUP($A226,netflixPart2!$A:$A,_xlfn.CHOOSECOLS(netflixPart2!$A:$F,_xlfn.XMATCH(netflixPart1!J$1,netflixPart2!$A$1:$F$1))),"Missing")} -> Comedies, Romantic Movies
A227: s165 | B227: Movie | C227: Mystery Men | D227: Kinka Usher | E227: United States | F227: {=IFERROR(_xlfn.XLOOKUP($A227,netflixPart2!$A:$A,_xlfn.CHOOSECOLS(netflixPart2!$A:$F,_xlfn.XMATCH(netflixPart1!F$1,netflixPart2!$A$1:$F$1))),"Missing")} -> 09/01/2021 | G227: {=DATE(IFERROR(_xlfn.XLOOKUP($A227,netflixPart2!$A:$A,_xlfn.CHOOSECOLS(netflixPart2!$A:$F,_xlfn.XMATCH(netflixPart1!G$1,netflixPart2!$A$1:$F$1))),"Missing"),1,1)} -> 36161 | H227: {=IFERROR(_xlfn.XLOOKUP($A227,netflixPart2!$A:$A,_xlfn.CHOOSECOLS(netflixPart2!$A:$F,_xlfn.XMATCH(netflixPart1!H$1,netflixPart2!$A$1:$F$1))),"Missing")} -> PG-13 | I227: {=IFERROR(_xlfn.XLOOKUP($A227,netflixPart2!$A:$A,_xlfn.CHOOSECOLS(netflixPart2!$A:$F,_xlfn.XMATCH(netflixPart1!I$1,netflixPart2!$A$1:$F$1))),"Missing")} -> 121 min | J227: {=IFERROR(_xlfn.XLOOKUP($A227,netflixPart2!$A:$A,_xlfn.CHOOSECOLS(netflixPart2!$A:$F,_xlfn.XMATCH(netflixPart1!J$1,netflixPart2!$A$1:$F$1))),"Missing")} -> Action & Adventure, Comedies
A228: s1472 | B228: Movie | C228: Best of Stand-Up 2020 | D228: Not Given | E228: Pakistan | F228: {=IFERROR(_xlfn.XLOOKUP($A228,netflixPart2!$A:$A,_xlfn.CHOOSECOLS(netflixPart2!$A:$F,_xlfn.XMATCH(netflixPart1!F$1,netflixPart2!$A$1:$F$1))),"Missing")} -> 12/31/2020 | G228: {=DATE(IFERROR(_xlfn.XLOOKUP($A228,netflixPart2!$A:$A,_xlfn.CHOOSECOLS(netflixPart2!$A:$F,_xlfn.XMATCH(netflixPart1!G$1,netflixPart2!$A$1:$F$1))),"Missing"),1,1)} -> 43831 | H228: {=IFERROR(_xlfn.XLOOKUP($A228,netflixPart2!$A:$A,_xlfn.CHOOSECOLS(netflixPart2!$A:$F,_xlfn.XMATCH(netflixPart1!H$1,netflixPart2!$A$1:$F$1))),"Missing")} -> TV-MA | I228: {=IFERROR(_xlfn.XLOOKUP($A228,netflixPart2!$A:$A,_xlfn.CHOOSECOLS(netflixPart2!$A:$F,_xlfn.XMATCH(netflixPart1!I$1,netflixPart2!$A$1:$F$1))),"Missing")} -> 77 min | J228: {=IFERROR(_xlfn.XLOOKUP($A228,netflixPart2!$A:$A,_xlfn.CHOOSECOLS(netflixPart2!$A:$F,_xlfn.XMATCH(netflixPart1!J$1,netflixPart2!$A$1:$F$1))),"Missing")} -> Stand-Up Comedy
A229: s167 | B229: Movie | C229: Once Upon a Time in America | D229: Sergio Leone | E229: Italy | F229: {=IFERROR(_xlfn.XLOOKUP($A229,netflixPart2!$A:$A,_xlfn.CHOOSECOLS(netflixPart2!$A:$F,_xlfn.XMATCH(netflixPart1!F$1,netflixPart2!$A$1:$F$1))),"Missing")} -> 09/01/2021 | G229: {=DATE(IFERROR(_xlfn.XLOOKUP($A229,netflixPart2!$A:$A,_xlfn.CHOOSECOLS(netflixPart2!$A:$F,_xlfn.XMATCH(netflixPart1!G$1,netflixPart2!$A$1:$F$1))),"Missing"),1,1)} -> 30682 | H229: {=IFERROR(_xlfn.XLOOKUP($A229,netflixPart2!$A:$A,_xlfn.CHOOSECOLS(netflixPart2!$A:$F,_xlfn.XMATCH(netflixPart1!H$1,netflixPart2!$A$1:$F$1))),"Missing")} -> R | I229: {=IFERROR(_xlfn.XLOOKUP($A229,netflixPart2!$A:$A,_xlfn.CHOOSECOLS(netflixPart2!$A:$F,_xlfn.XMATCH(netflixPart1!I$1,netflixPart2!$A$1:$F$1))),"Missing")} -> 229 min | J229: {=IFERROR(_xlfn.XLOOKUP($A229,netflixPart2!$A:$A,_xlfn.CHOOSECOLS(netflixPart2!$A:$F,_xlfn.XMATCH(netflixPart1!J$1,netflixPart2!$A$1:$F$1))),"Missing")} -> Classic Movies, Dramas
A230: s168 | B230: Movie | C230: Open Season 2 | D230: Matthew O'Callaghan, Todd Wilderman | E230: United States | F230: {=IFERROR(_xlfn.XLOOKUP($A230,netflixPart2!$A:$A,_xlfn.CHOOSECOLS(netflixPart2!$A:$F,_xlfn.XMATCH(netflixPart1!F$1,netflixPart2!$A$1:$F$1))),"Missing")} -> 09/01/2021 | G230: {=DATE(IFERROR(_xlfn.XLOOKUP($A230,netflixPart2!$A:$A,_xlfn.CHOOSECOLS(netflixPart2!$A:$F,_xlfn.XMATCH(netflixPart1!G$1,netflixPart2!$A$1:$F$1))),"Missing"),1,1)} -> 39448 | H230: {=IFERROR(_xlfn.XLOOKUP($A230,netflixPart2!$A:$A,_xlfn.CHOOSECOLS(netflixPart2!$A:$F,_xlfn.XMATCH(netflixPart1!H$1,netflixPart2!$A$1:$F$1))),"Missing")} -> PG | I230: {=IFERROR(_xlfn.XLOOKUP($A230,netflixPart2!$A:$A,_xlfn.CHOOSECOLS(netflixPart2!$A:$F,_xlfn.XMATCH(netflixPart1!I$1,netflixPart2!$A$1:$F$1))),"Missing")} -> 76 min | J230: {=IFERROR(_xlfn.XLOOKUP($A230,netflixPart2!$A:$A,_xlfn.CHOOSECOLS(netflixPart2!$A:$F,_xlfn.XMATCH(netflixPart1!J$1,netflixPart2!$A$1:$F$1))),"Missing")} -> Children & Family Movies, Comedies
A231: s169 | B231: Movie | C231: Osmosis Jones | D231: Bobby Farrelly, Peter Farrelly | E231: United States | F231: {=IFERROR(_xlfn.XLOOKUP($A231,netflixPart2!$A:$A,_xlfn.CHOOSECOLS(netflixPart2!$A:$F,_xlfn.XMATCH(netflixPart1!F$1,netflixPart2!$A$1:$F$1))),"Missing")} -> 09/01/2021 | G231: {=DATE(IFERROR(_xlfn.XLOOKUP($A231,netflixPart2!$A:$A,_xlfn.CHOOSECOLS(netflixPart2!$A:$F,_xlfn.XMATCH(netflixPart1!G$1,netflixPart2!$A$1:$F$1))),"Missing"),1,1)} -> 36892 | H231: {=IFERROR(_xlfn.XLOOKUP($A231,netflixPart2!$A:$A,_xlfn.CHOOSECOLS(netflixPart2!$A:$F,_xlfn.XMATCH(netflixPart1!H$1,netflixPart2!$A$1:$F$1))),"Missing")} -> PG | I231: {=IFERROR(_xlfn.XLOOKUP($A231,netflixPart2!$A:$A,_xlfn.CHOOSECOLS(netflixPart2!$A:$F,_xlfn.XMATCH(netflixPart1!I$1,netflixPart2!$A$1:$F$1))),"Missing")} -> 95 min | J231: {=IFERROR(_xlfn.XLOOKUP($A231,netflixPart2!$A:$A,_xlfn.CHOOSECOLS(netflixPart2!$A:$F,_xlfn.XMATCH(netflixPart1!J$1,netflixPart2!$A$1:$F$1))),"Missing")} -> Action & Adventure, Children & Family Movies, Comedies
A232: s170 | B232: Movie | C232: Poseidon | D232: Wolfgang Petersen | E232: United States | F232: {=IFERROR(_xlfn.XLOOKUP($A232,netflixPart2!$A:$A,_xlfn.CHOOSECOLS(netflixPart2!$A:$F,_xlfn.XMATCH(netflixPart1!F$1,netflixPart2!$A$1:$F$1))),"Missing")} -> 09/01/2021 | G232: {=DATE(IFERROR(_xlfn.XLOOKUP($A232,netflixPart2!$A:$A,_xlfn.CHOOSECOLS(netflixPart2!$A:$F,_xlfn.XMATCH(netflixPart1!G$1,netflixPart2!$A$1:$F$1))),"Missing"),1,1)} -> 38718 | H232: {=IFERROR(_xlfn.XLOOKUP($A232,netflixPart2!$A:$A,_xlfn.CHOOSECOLS(netflixPart2!$A:$F,_xlfn.XMATCH(netflixPart1!H$1,netflixPart2!$A$1:$F$1))),"Missing")} -> PG-13 | I232: {=IFERROR(_xlfn.XLOOKUP($A232,netflixPart2!$A:$A,_xlfn.CHOOSECOLS(netflixPart2!$A:$F,_xlfn.XMATCH(netflixPart1!I$1,netflixPart2!$A$1:$F$1))),"Missing")} -> 98 min | J232: {=IFERROR(_xlfn.XLOOKUP($A232,netflixPart2!$A:$A,_xlfn.CHOOSECOLS(netflixPart2!$A:$F,_xlfn.XMATCH(netflixPart1!J$1,netflixPart2!$A$1:$F$1))),"Missing")} -> Action & Adventure, Dramas
A233: s1483 | B233: TV Show | C233: Transformers: War for Cybertron: Earthrise | D233: Not Given | E233: Pakistan | F233: {=IFERROR(_xlfn.XLOOKUP($A233,netflixPart2!$A:$A,_xlfn.CHOOSECOLS(netflixPart2!$A:$F,_xlfn.XMATCH(netflixPart1!F$1,netflixPart2!$A$1:$F$1))),"Missing")} -> 12/30/2020 | G233: {=DATE(IFERROR(_xlfn.XLOOKUP($A233,netflixPart2!$A:$A,_xlfn.CHOOSECOLS(netflixPart2!$A:$F,_xlfn.XMATCH(netflixPart1!G$1,netflixPart2!$A$1:$F$1))),"Missing"),1,1)} -> 43831 | H233: {=IFERROR(_xlfn.XLOOKUP($A233,netflixPart2!$A:$A,_xlfn.CHOOSECOLS(netflixPart2!$A:$F,_xlfn.XMATCH(netflixPart1!H$1,netflixPart2!$A$1:$F$1))),"Missing")} -> TV-Y7 | I233: {=IFERROR(_xlfn.XLOOKUP($A233,netflixPart2!$A:$A,_xlfn.CHOOSECOLS(netflixPart2!$A:$F,_xlfn.XMATCH(netflixPart1!I$1,netflixPart2!$A$1:$F$1))),"Missing")} -> 1 Season | J233: {=IFERROR(_xlfn.XLOOKUP($A233,netflixPart2!$A:$A,_xlfn.CHOOSECOLS(netflixPart2!$A:$F,_xlfn.XMATCH(netflixPart1!J$1,netflixPart2!$A$1:$F$1))),"Missing")} -> Anime Series
A234: s1586 | B234: TV Show | C234: Manhunt: Deadly Games | D234: Not Given | E234: Pakistan | F234: {=IFERROR(_xlfn.XLOOKUP($A234,netflixPart2!$A:$A,_xlfn.CHOOSECOLS(netflixPart2!$A:$F,_xlfn.XMATCH(netflixPart1!F$1,netflixPart2!$A$1:$F$1))),"Missing")} -> 12/07/2020 | G234: {=DATE(IFERROR(_xlfn.XLOOKUP($A234,netflixPart2!$A:$A,_xlfn.CHOOSECOLS(netflixPart2!$A:$F,_xlfn.XMATCH(netflixPart1!G$1,netflixPart2!$A$1:$F$1))),"Missing"),1,1)} -> 43831 | H234: {=IFERROR(_xlfn.XLOOKUP($A234,netflixPart2!$A:$A,_xlfn.CHOOSECOLS(netflixPart2!$A:$F,_xlfn.XMATCH(netflixPart1!H$1,netflixPart2!$A$1:$F$1))),"Missing")} -> TV-14 | I234: {=IFERROR(_xlfn.XLOOKUP($A234,netflixPart2!$A:$A,_xlfn.CHOOSECOLS(netflixPart2!$A:$F,_xlfn.XMATCH(netflixPart1!I$1,netflixPart2!$A$1:$F$1))),"Missing")} -> 1 Season | J234: {=IFERROR(_xlfn.XLOOKUP($A234,netflixPart2!$A:$A,_xlfn.CHOOSECOLS(netflixPart2!$A:$F,_xlfn.XMATCH(netflixPart1!J$1,netflixPart2!$A$1:$F$1))),"Missing")} -> Crime TV Shows, TV Dramas, TV Mysteries
... A394: s3988 | B394: Movie | C394: Antoine Griezmann: The Making of a Legend | D394: Not Given | E394: Pakistan | F394: {=IFERROR(_xlfn.XLOOKUP($A394,netflixPart2!$A:$A,_xlfn.CHOOSECOLS(netflixPart2!$A:$F,_xlfn.XMATCH(netflixPart1!F$1,netflixPart2!$A$1:$F$1))),"Missing")} -> 3/21/2019 | G394: {=DATE(IFERROR(_xlfn.XLOOKUP($A394,netflixPart2!$A:$A,_xlfn.CHOOSECOLS(netflixPart2!$A:$F,_xlfn.XMATCH(netflixPart1!G$1,netflixPart2!$A$1:$F$1))),"Missing"),1,1)} -> 43466 | H394: {=IFERROR(_xlfn.XLOOKUP($A394,netflixPart2!$A:$A,_xlfn.CHOOSECOLS(netflixPart2!$A:$F,_xlfn.XMATCH(netflixPart1!H$1,netflixPart2!$A$1:$F$1))),"Missing")} -> TV-PG | I394: {=IFERROR(_xlfn.XLOOKUP($A394,netflixPart2!$A:$A,_xlfn.CHOOSECOLS(netflixPart2!$A:$F,_xlfn.XMATCH(netflixPart1!I$1,netflixPart2!$A$1:$F$1))),"Missing")} -> 60 min | J394: {=IFERROR(_xlfn.XLOOKUP($A394,netflixPart2!$A:$A,_xlfn.CHOOSECOLS(netflixPart2!$A:$F,_xlfn.XMATCH(netflixPart1!J$1,netflixPart2!$A$1:$F$1))),"Missing")} -> Documentaries, International Movies, Sports Movies
A395: s3997 | B395: TV Show | C395: 09-Feb | D395: Not Given | E395: Pakistan | F395: {=IFERROR(_xlfn.XLOOKUP($A395,netflixPart2!$A:$A,_xlfn.CHOOSECOLS(netflixPart2!$A:$F,_xlfn.XMATCH(netflixPart1!F$1,netflixPart2!$A$1:$F$1))),"Missing")} -> 3/20/2019 | G395: {=DATE(IFERROR(_xlfn.XLOOKUP($A395,netflixPart2!$A:$A,_xlfn.CHOOSECOLS(netflixPart2!$A:$F,_xlfn.XMATCH(netflixPart1!G$1,netflixPart2!$A$1:$F$1))),"Missing"),1,1)} -> 43101 | H395: {=IFERROR(_xlfn.XLOOKUP($A395,netflixPart2!$A:$A,_xlfn.CHOOSECOLS(netflixPart2!$A:$F,_xlfn.XMATCH(netflixPart1!H$1,netflixPart2!$A$1:$F$1))),"Missing")} -> TV-14 | I395: {=IFERROR(_xlfn.XLOOKUP($A395,netflixPart2!$A:$A,_xlfn.CHOOSECOLS(netflixPart2!$A:$F,_xlfn.XMATCH(netflixPart1!I$1,netflixPart2!$A$1:$F$1))),"Missing")} -> 1 Season | J395: {=IFERROR(_xlfn.XLOOKUP($A395,netflixPart2!$A:$A,_xlfn.CHOOSECOLS(netflixPart2!$A:$F,_xlfn.XMATCH(netflixPart1!J$1,netflixPart2!$A$1:$F$1))),"Missing")} -> International TV Shows, TV Dramas | K395: =_xlfn.TEXTJOIN("|",FALSE,B395:J395) -> TV Show|09-Feb|Not Given|Pakistan|3/20/2019|43101|TV-14|1 Season|International TV Shows, TV Dramas
A396: s4013 | B396: TV Show | C396: My Pride | D396: Not Given | E396: Pakistan | F396: {=IFERROR(_xlfn.XLOOKUP($A396,netflixPart2!$A:$A,_xlfn.CHOOSECOLS(netflixPart2!$A:$F,_xlfn.XMATCH(netflixPart1!F$1,netflixPart2!$A$1:$F$1))),"Missing")} -> 3/15/2019 | G396: {=DATE(IFERROR(_xlfn.XLOOKUP($A396,netflixPart2!$A:$A,_xlfn.CHOOSECOLS(netflixPart2!$A:$F,_xlfn.XMATCH(netflixPart1!G$1,netflixPart2!$A$1:$F$1))),"Missing"),1,1)} -> 43101 | H396: {=IFERROR(_xlfn.XLOOKUP($A396,netflixPart2!$A:$A,_xlfn.CHOOSECOLS(netflixPart2!$A:$F,_xlfn.XMATCH(netflixPart1!H$1,netflixPart2!$A$1:$F$1))),"Missing")} -> TV-14 | I396: {=IFERROR(_xlfn.XLOOKUP($A396,netflixPart2!$A:$A,_xlfn.CHOOSECOLS(netflixPart2!$A:$F,_xlfn.XMATCH(netflixPart1!I$1,netflixPart2!$A$1:$F$1))),"Missing")} -> 1 Season | J396: {=IFERROR(_xlfn.XLOOKUP($A396,netflixPart2!$A:$A,_xlfn.CHOOSECOLS(netflixPart2!$A:$F,_xlfn.XMATCH(netflixPart1!J$1,netflixPart2!$A$1:$F$1))),"Missing")} -> International TV Shows, TV Dramas
A397: s4016 | B397: TV Show | C397: The Disappearance of Madeleine McCann | D397: Not Given | E397: Pakistan | F397: {=IFERROR(_xlfn.XLOOKUP($A397,netflixPart2!$A:$A,_xlfn.CHOOSECOLS(netflixPart2!$A:$F,_xlfn.XMATCH(netflixPart1!F$1,netflixPart2!$A$1:$F$1))),"Missing")} -> 3/15/2019 | G397: {=DATE(IFERROR(_xlfn.XLOOKUP($A397,netflixPart2!$A:$A,_xlfn.CHOOSECOLS(netflixPart2!$A:$F,_xlfn.XMATCH(netflixPart1!G$1,netflixPart2!$A$1:$F$1))),"Missing"),1,1)} -> 43466 | H397: {=IFERROR(_xlfn.XLOOKUP($A397,netflixPart2!$A:$A,_xlfn.CHOOSECOLS(netflixPart2!$A:$F,_xlfn.XMATCH(netflixPart1!H$1,netflixPart2!$A$1:$F$1))),"Missing")} -> TV-14 | I397: {=IFERROR(_xlfn.XLOOKUP($A397,netflixPart2!$A:$A,_xlfn.CHOOSECOLS(netflixPart2!$A:$F,_xlfn.XMATCH(netflixPart1!I$1,netflixPart2!$A$1:$F$1))),"Missing")} -> 1 Season | J397: {=IFERROR(_xlfn.XLOOKUP($A397,netflixPart2!$A:$A,_xlfn.CHOOSECOLS(netflixPart2!$A:$F,_xlfn.XMATCH(netflixPart1!J$1,netflixPart2!$A$1:$F$1))),"Missing")} -> Crime TV Shows, Docuseries
A398: s4036 | B398: TV Show | C398: The Confrontation | D398: Not Given | E398: Pakistan | F398: {=IFERROR(_xlfn.XLOOKUP($A398,netflixPart2!$A:$A,_xlfn.CHOOSECOLS(netflixPart2!$A:$F,_xlfn.XMATCH(netflixPart1!F$1,netflixPart2!$A$1:$F$1))),"Missing")} -> 03/08/2019 | G398: {=DATE(IFERROR(_xlfn.XLOOKUP($A398,netflixPart2!$A:$A,_xlfn.CHOOSECOLS(netflixPart2!$A:$F,_xlfn.XMATCH(netflixPart1!G$1,netflixPart2!$A$1:$F$1))),"Missing"),1,1)} -> 43101 | H398: {=IFERROR(_xlfn.XLOOKUP($A398,netflixPart2!$A:$A,_xlfn.CHOOSECOLS(netflixPart2!$A:$F,_xlfn.XMATCH(netflixPart1!H$1,netflixPart2!$A$1:$F$1))),"Missing")} -> TV-PG | I398: {=IFERROR(_xlfn.XLOOKUP($A398,netflixPart2!$A:$A,_xlfn.CHOOSECOLS(netflixPart2!$A:$F,_xlfn.XMATCH(netflixPart1!I$1,netflixPart2!$A$1:$F$1))),"Missing")} -> 1 Season | J398: {=IFERROR(_xlfn.XLOOKUP($A398,netflixPart2!$A:$A,_xlfn.CHOOSECOLS(netflixPart2!$A:$F,_xlfn.XMATCH(netflixPart1!J$1,netflixPart2!$A$1:$F$1))),"Missing")} -> International TV Shows, TV Dramas
A399: s4056 | B399: TV Show | C399: Larva Island | D399: Not Given | E399: Pakistan | F399: {=IFERROR(_xlfn.XLOOKUP($A399,netflixPart2!$A:$A,_xlfn.CHOOSECOLS(netflixPart2!$A:$F,_xlfn.XMATCH(netflixPart1!F$1,netflixPart2!$A$1:$F$1))),"Missing")} -> 03/01/2019 | G399: {=DATE(IFERROR(_xlfn.XLOOKUP($A399,netflixPart2!$A:$A,_xlfn.CHOOSECOLS(netflixPart2!$A:$F,_xlfn.XMATCH(netflixPart1!G$1,netflixPart2!$A$1:$F$1))),"Missing"),1,1)} -> 43466 | H399: {=IFERROR(_xlfn.XLOOKUP($A399,netflixPart2!$A:$A,_xlfn.CHOOSECOLS(netflixPart2!$A:$F,_xlfn.XMATCH(netflixPart1!H$1,netflixPart2!$A$1:$F$1))),"Missing")} -> TV-Y7 | I399: {=IFERROR(_xlfn.XLOOKUP($A399,netflixPart2!$A:$A,_xlfn.CHOOSECOLS(netflixPart2!$A:$F,_xlfn.XMATCH(netflixPart1!I$1,netflixPart2!$A$1:$F$1))),"Missing")} -> 2 Seasons | J399: {=IFERROR(_xlfn.XLOOKUP($A399,netflixPart2!$A:$A,_xlfn.CHOOSECOLS(netflixPart2!$A:$F,_xlfn.XMATCH(netflixPart1!J$1,netflixPart2!$A$1:$F$1))),"Missing")} -> Kids' TV, Korean TV Shows, TV Comedies
A400: s4057 | B400: TV Show | C400: Losers | D400: Not Given | E400: Pakistan | F400: {=IFERROR(_xlfn.XLOOKUP($A400,netflixPart2!$A:$A,_xlfn.CHOOSECOLS(netflixPart2!$A:$F,_xlfn.XMATCH(netflixPart1!F$1,netflixPart2!$A$1:$F$1))),"Missing")} -> 03/01/2019 | G400: {=DATE(IFERROR(_xlfn.XLOOKUP($A400,netflixPart2!$A:$A,_xlfn.CHOOSECOLS(netflixPart2!$A:$F,_xlfn.XMATCH(netflixPart1!G$1,netflixPart2!$A$1:$F$1))),"Missing"),1,1)} -> 43466 | H400: {=IFERROR(_xlfn.XLOOKUP($A400,netflixPart2!$A:$A,_xlfn.CHOOSECOLS(netflixPart2!$A:$F,_xlfn.XMATCH(netflixPart1!H$1,netflixPart2!$A$1:$F$1))),"Missing")} -> TV-MA | I400: {=IFERROR(_xlfn.XLOOKUP($A400,netflixPart2!$A:$A,_xlfn.CHOOSECOLS(netflixPart2!$A:$F,_xlfn.XMATCH(netflixPart1!I$1,netflixPart2!$A$1:$F$1))),"Missing")} -> 1 Season | J400: {=IFERROR(_xlfn.XLOOKUP($A400,netflixPart2!$A:$A,_xlfn.CHOOSECOLS(netflixPart2!$A:$F,_xlfn.XMATCH(netflixPart1!J$1,netflixPart2!$A$1:$F$1))),"Missing")} -> Docuseries
A401: s4106 | B401: TV Show | C401: Larry Charles' Dangerous World of Comedy | D401: Not Given | E401: Pakistan | F401: {=IFERROR(_xlfn.XLOOKUP($A401,netflixPart2!$A:$A,_xlfn.CHOOSECOLS(netflixPart2!$A:$F,_xlfn.XMATCH(netflixPart1!F$1,netflixPart2!$A$1:$F$1))),"Missing")} -> 2/15/2019 | G401: {=DATE(IFERROR(_xlfn.XLOOKUP($A401,netflixPart2!$A:$A,_xlfn.CHOOSECOLS(netflixPart2!$A:$F,_xlfn.XMATCH(netflixPart1!G$1,netflixPart2!$A$1:$F$1))),"Missing"),1,1)} -> 43466 | H401: {=IFERROR(_xlfn.XLOOKUP($A401,netflixPart2!$A:$A,_xlfn.CHOOSECOLS(netflixPart2!$A:$F,_xlfn.XMATCH(netflixPart1!H$1,netflixPart2!$A$1:$F$1))),"Missing")} -> TV-MA | I401: {=IFERROR(_xlfn.XLOOKUP($A401,netflixPart2!$A:$A,_xlfn.CHOOSECOLS(netflixPart2!$A:$F,_xlfn.XMATCH(netflixPart1!I$1,netflixPart2!$A$1:$F$1))),"Missing")} -> 1 Season | J401: {=IFERROR(_xlfn.XLOOKUP($A401,netflixPart2!$A:$A,_xlfn.CHOOSECOLS(netflixPart2!$A:$F,_xlfn.XMATCH(netflixPart1!J$1,netflixPart2!$A$1:$F$1))),"Missing")} -> Docuseries, TV Comedies
A402: s4110 | B402: TV Show | C402: The 43 | D402: Not Given | E402: Pakistan | F402: {=IFERROR(_xlfn.XLOOKUP($A402,netflixPart2!$A:$A,_xlfn.CHOOSECOLS(netflixPart2!$A:$F,_xlfn.XMATCH(netflixPart1!F$1,netflixPart2!$A$1:$F$1))),"Missing")} -> 2/15/2019 | G402: {=DATE(IFERROR(_xlfn.XLOOKUP($A402,netflixPart2!$A:$A,_xlfn.CHOOSECOLS(netflixPart2!$A:$F,_xlfn.XMATCH(netflixPart1!G$1,netflixPart2!$A$1:$F$1))),"Missing"),1,1)} -> 43466 | H402: {=IFERROR(_xlfn.XLOOKUP($A402,netflixPart2!$A:$A,_xlfn.CHOOSECOLS(netflixPart2!$A:$F,_xlfn.XMATCH(netflixPart1!H$1,netflixPart2!$A$1:$F$1))),"Missing")} -> TV-MA | I402: {=IFERROR(_xlfn.XLOOKUP($A402,netflixPart2!$A:$A,_xlfn.CHOOSECOLS(netflixPart2!$A:$F,_xlfn.XMATCH(netflixPart1!I$1,netflixPart2!$A$1:$F$1))),"Missing")} -> 1 Season | J402: {=IFERROR(_xlfn.XLOOKUP($A402,netflixPart2!$A:$A,_xlfn.CHOOSECOLS(netflixPart2!$A:$F,_xlfn.XMATCH(netflixPart1!J$1,netflixPart2!$A$1:$F$1))),"Missing")} -> Crime TV Shows, Docuseries, International TV Shows
A403: s4718 | B403: TV Show | C403: Dinotrux Supercharged | D403: Not Given | E403: Pakistan | F403: {=IFERROR(_xlfn.XLOOKUP($A403,netflixPart2!$A:$A,_xlfn.CHOOSECOLS(netflixPart2!$A:$F,_xlfn.XMATCH(netflixPart1!F$1,netflixPart2!$A$1:$F$1))),"Missing")} -> 08/03/2018 | G403: {=DATE(IFERROR(_xlfn.XLOOKUP($A403,netflixPart2!$A:$A,_xlfn.CHOOSECOLS(netflixPart2!$A:$F,_xlfn.XMATCH(netflixPart1!G$1,netflixPart2!$A$1:$F$1))),"Missing"),1,1)} -> 43101 | H403: {=IFERROR(_xlfn.XLOOKUP($A403,netflixPart2!$A:$A,_xlfn.CHOOSECOLS(netflixPart2!$A:$F,_xlfn.XMATCH(netflixPart1!H$1,netflixPart2!$A$1:$F$1))),"Missing")} -> TV-Y7 | I403: {=IFERROR(_xlfn.XLOOKUP($A403,netflixPart2!$A:$A,_xlfn.CHOOSECOLS(netflixPart2!$A:$F,_xlfn.XMATCH(netflixPart1!I$1,netflixPart2!$A$1:$F$1))),"Missing")} -> 3 Seasons | J403: {=IFERROR(_xlfn.XLOOKUP($A403,netflixPart2!$A:$A,_xlfn.CHOOSECOLS(netflixPart2!$A:$F,_xlfn.XMATCH(netflixPart1!J$1,netflixPart2!$A$1:$F$1))),"Missing")} -> Kids' TV
A404: s4150 | B404: TV Show | C404: Paprika | D404: Not Given | E404: Pakistan | F404: {=IFERROR(_xlfn.XLOOKUP($A404,netflixPart2!$A:$A,_xlfn.CHOOSECOLS(netflixPart2!$A:$F,_xlfn.XMATCH(netflixPart1!F$1,netflixPart2!$A$1:$F$1))),"Missing")} -> 1/31/2019 | G404: {=DATE(IFERROR(_xlfn.XLOOKUP($A404,netflixPart2!$A:$A,_xlfn.CHOOSECOLS(netflixPart2!$A:$F,_xlfn.XMATCH(netflixPart1!G$1,netflixPart2!$A$1:$F$1))),"Missing"),1,1)} -> 43101 | H404: {=IFERROR(_xlfn.XLOOKUP($A404,netflixPart2!$A:$A,_xlfn.CHOOSECOLS(netflixPart2!$A:$F,_xlfn.XMATCH(netflixPart1!H$1,netflixPart2!$A$1:$F$1))),"Missing")} -> TV-Y | I404: {=IFERROR(_xlfn.XLOOKUP($A404,netflixPart2!$A:$A,_xlfn.CHOOSECOLS(netflixPart2!$A:$F,_xlfn.XMATCH(netflixPart1!I$1,netflixPart2!$A$1:$F$1))),"Missing")} -> 1 Season | J404: {=IFERROR(_xlfn.XLOOKUP($A404,netflixPart2!$A:$A,_xlfn.CHOOSECOLS(netflixPart2!$A:$F,_xlfn.XMATCH(netflixPart1!J$1,netflixPart2!$A$1:$F$1))),"Missing")} -> Kids' TV
A405: s291 | B405: Movie | C405: Untold: Malice at the Palace | D405: Floyd Russ | E405: United States | F405: {=IFERROR(_xlfn.XLOOKUP($A405,netflixPart2!$A:$A,_xlfn.CHOOSECOLS(netflixPart2!$A:$F,_xlfn.XMATCH(netflixPart1!F$1,netflixPart2!$A$1:$F$1))),"Missing")} -> 08/10/2021 | G405: {=DATE(IFERROR(_xlfn.XLOOKUP($A405,netflixPart2!$A:$A,_xlfn.CHOOSECOLS(netflixPart2!$A:$F,_xlfn.XMATCH(netflixPart1!G$1,netflixPart2!$A$1:$F$1))),"Missing"),1,1)} -> 44197 | H405: {=IFERROR(_xlfn.XLOOKUP($A405,netflixPart2!$A:$A,_xlfn.CHOOSECOLS(netflixPart2!$A:$F,_xlfn.XMATCH(netflixPart1!H$1,netflixPart2!$A$1:$F$1))),"Missing")} -> TV-MA | I405: {=IFERROR(_xlfn.XLOOKUP($A405,netflixPart2!$A:$A,_xlfn.CHOOSECOLS(netflixPart2!$A:$F,_xlfn.XMATCH(netflixPart1!I$1,netflixPart2!$A$1:$F$1))),"Missing")} -> 70 min | J405: {=IFERROR(_xlfn.XLOOKUP($A405,netflixPart2!$A:$A,_xlfn.CHOOSECOLS(netflixPart2!$A:$F,_xlfn.XMATCH(netflixPart1!J$1,netflixPart2!$A$1:$F$1))),"Missing")} -> Documentaries, Sports Movies
A406: s4172 | B406: TV Show | C406: The Perfect Match | D406: Not Given | E406: Pakistan | F406: {=IFERROR(_xlfn.XLOOKUP($A406,netflixPart2!$A:$A,_xlfn.CHOOSECOLS(netflixPart2!$A:$F,_xlfn.XMATCH(netflixPart1!F$1,netflixPart2!$A$1:$F$1))),"Missing")} -> 1/25/2019 | G406: {=DATE(IFERROR(_xlfn.XLOOKUP($A406,netflixPart2!$A:$A,_xlfn.CHOOSECOLS(netflixPart2!$A:$F,_xlfn.XMATCH(netflixPart1!G$1,netflixPart2!$A$1:$F$1))),"Missing"),1,1)} -> 42736 | H406: {=IFERROR(_xlfn.XLOOKUP($A406,netflixPart2!$A:$A,_xlfn.CHOOSECOLS(netflixPart2!$A:$F,_xlfn.XMATCH(netflixPart1!H$1,netflixPart2!$A$1:$F$1))),"Missing")} -> TV-14 | I406: {=IFERROR(_xlfn.XLOOKUP($A406,netflixPart2!$A:$A,_xlfn.CHOOSECOLS(netflixPart2!$A:$F,_xlfn.XMATCH(netflixPart1!I$1,netflixPart2!$A$1:$F$1))),"Missing")} -> 1 Season | J406: {=IFERROR(_xlfn.XLOOKUP($A406,netflixPart2!$A:$A,_xlfn.CHOOSECOLS(netflixPart2!$A:$F,_xlfn.XMATCH(netflixPart1!J$1,netflixPart2!$A$1:$F$1))),"Missing")} -> International TV Shows, Romantic TV Shows, TV Comedies
A407: s293 | B407: Movie | C407: Quartet | D407: Dustin Hoffman | E407: United Kingdom | F407: {=IFERROR(_xlfn.XLOOKUP($A407,netflixPart2!$A:$A,_xlfn.CHOOSECOLS(netflixPart2!$A:$F,_xlfn.XMATCH(netflixPart1!F$1,netflixPart2!$A$1:$F$1))),"Missing")} -> 08/08/2021 | G407: {=DATE(IFERROR(_xlfn.XLOOKUP($A407,netflixPart2!$A:$A,_xlfn.CHOOSECOLS(netflixPart2!$A:$F,_xlfn.XMATCH(netflixPart1!G$1,netflixPart2!$A$1:$F$1))),"Missing"),1,1)} -> 40909 | H407: {=IFERROR(_xlfn.XLOOKUP($A407,netflixPart2!$A:$A,_xlfn.CHOOSECOLS(netflixPart2!$A:$F,_xlfn.XMATCH(netflixPart1!H$1,netflixPart2!$A$1:$F$1))),"Missing")} -> PG-13 | I407: {=IFERROR(_xlfn.XLOOKUP($A407,netflixPart2!$A:$A,_xlfn.CHOOSECOLS(netflixPart2!$A:$F,_xlfn.XMATCH(netflixPart1!I$1,netflixPart2!$A$1:$F$1))),"Missing")} -> 98 min | J407: {=IFERROR(_xlfn.XLOOKUP($A407,netflixPart2!$A:$A,_xlfn.CHOOSECOLS(netflixPart2!$A:$F,_xlfn.XMATCH(netflixPart1!J$1,netflixPart2!$A$1:$F$1))),"Missing")} -> Comedies, Dramas, Independent Movies
... A416: s303 | B416: Movie | C416: City of God: 10 Years Later | D416: Cavi Borges, Luciano Vidigal | E416: Brazil | F416: {=IFERROR(_xlfn.XLOOKUP($A416,netflixPart2!$A:$A,_xlfn.CHOOSECOLS(netflixPart2!$A:$F,_xlfn.XMATCH(netflixPart1!F$1,netflixPart2!$A$1:$F$1))),"Missing")} -> 08/05/2021 | G416: {=DATE(IFERROR(_xlfn.XLOOKUP($A416,netflixPart2!$A:$A,_xlfn.CHOOSECOLS(netflixPart2!$A:$F,_xlfn.XMATCH(netflixPart1!G$1,netflixPart2!$A$1:$F$1))),"Missing"),1,1)} -> 41275 | H416: {=IFERROR(_xlfn.XLOOKUP($A416,netflixPart2!$A:$A,_xlfn.CHOOSECOLS(netflixPart2!$A:$F,_xlfn.XMATCH(netflixPart1!H$1,netflixPart2!$A$1:$F$1))),"Missing")} -> TV-MA | I416: {=IFERROR(_xlfn.XLOOKUP($A416,netflixPart2!$A:$A,_xlfn.CHOOSECOLS(netflixPart2!$A:$F,_xlfn.XMATCH(netflixPart1!I$1,netflixPart2!$A$1:$F$1))),"Missing")} -> 69 min | J416: {=IFERROR(_xlfn.XLOOKUP($A416,netflixPart2!$A:$A,_xlfn.CHOOSECOLS(netflixPart2!$A:$F,_xlfn.XMATCH(netflixPart1!J$1,netflixPart2!$A$1:$F$1))),"Missing")} -> Documentaries, International Movies
A417: s304 | B417: Movie | C417: Esperando la carroza | D417: Alejandro Doria | E417: Argentina | F417: {=IFERROR(_xlfn.XLOOKUP($A417,netflixPart2!$A:$A,_xlfn.CHOOSECOLS(netflixPart2!$A:$F,_xlfn.XMATCH(netflixPart1!F$1,netflixPart2!$A$1:$F$1))),"Missing")} -> 08/05/2021 | G417: {=DATE(IFERROR(_xlfn.XLOOKUP($A417,netflixPart2!$A:$A,_xlfn.CHOOSECOLS(netflixPart2!$A:$F,_xlfn.XMATCH(netflixPart1!G$1,netflixPart2!$A$1:$F$1))),"Missing"),1,1)} -> 31048 | H417: {=IFERROR(_xlfn.XLOOKUP($A417,netflixPart2!$A:$A,_xlfn.CHOOSECOLS(netflixPart2!$A:$F,_xlfn.XMATCH(netflixPart1!H$1,netflixPart2!$A$1:$F$1))),"Missing")} -> TV-MA | I417: {=IFERROR(_xlfn.XLOOKUP($A417,netflixPart2!$A:$A,_xlfn.CHOOSECOLS(netflixPart2!$A:$F,_xlfn.XMATCH(netflixPart1!I$1,netflixPart2!$A$1:$F$1))),"Missing")} -> 95 min | J417: {=IFERROR(_xlfn.XLOOKUP($A417,netflixPart2!$A:$A,_xlfn.CHOOSECOLS(netflixPart2!$A:$F,_xlfn.XMATCH(netflixPart1!J$1,netflixPart2!$A$1:$F$1))),"Missing")} -> Comedies, Cult Movies, International Movies | K417: =_xlfn.TEXTJOIN("|",FALSE,B417:J417) -> Movie|Esperando la carroza|Alejandro Doria|Argentina|08/05/2021|31048|TV-MA|95 min|Comedies, Cult Movies, International Movies
A418: s305 | B418: Movie | C418: Lady Boss: The Jackie Collins Story | D418: Laura Fairrie | E418: United Kingdom | F418: {=IFERROR(_xlfn.XLOOKUP($A418,netflixPart2!$A:$A,_xlfn.CHOOSECOLS(netflixPart2!$A:$F,_xlfn.XMATCH(netflixPart1!F$1,netflixPart2!$A$1:$F$1))),"Missing")} -> 08/05/2021 | G418: {=DATE(IFERROR(_xlfn.XLOOKUP($A418,netflixPart2!$A:$A,_xlfn.CHOOSECOLS(netflixPart2!$A:$F,_xlfn.XMATCH(netflixPart1!G$1,netflixPart2!$A$1:$F$1))),"Missing"),1,1)} -> 44197 | H418: {=IFERROR(_xlfn.XLOOKUP($A418,netflixPart2!$A:$A,_xlfn.CHOOSECOLS(netflixPart2!$A:$F,_xlfn.XMATCH(netflixPart1!H$1,netflixPart2!$A$1:$F$1))),"Missing")} -> TV-14 | I418: {=IFERROR(_xlfn.XLOOKUP($A418,netflixPart2!$A:$A,_xlfn.CHOOSECOLS(netflixPart2!$A:$F,_xlfn.XMATCH(netflixPart1!I$1,netflixPart2!$A$1:$F$1))),"Missing")} -> 97 min | J418: {=IFERROR(_xlfn.XLOOKUP($A418,netflixPart2!$A:$A,_xlfn.CHOOSECOLS(netflixPart2!$A:$F,_xlfn.XMATCH(netflixPart1!J$1,netflixPart2!$A$1:$F$1))),"Missing")} -> Documentaries
A419: s306 | B419: Movie | C419: Tango Feroz | D419: Marcelo Piñeyro | E419: Argentina | F419: {=IFERROR(_xlfn.XLOOKUP($A419,netflixPart2!$A:$A,_xlfn.CHOOSECOLS(netflixPart2!$A:$F,_xlfn.XMATCH(netflixPart1!F$1,netflixPart2!$A$1:$F$1))),"Missing")} -> 08/05/2021 | G419: {=DATE(IFERROR(_xlfn.XLOOKUP($A419,netflixPart2!$A:$A,_xlfn.CHOOSECOLS(netflixPart2!$A:$F,_xlfn.XMATCH(netflixPart1!G$1,netflixPart2!$A$1:$F$1))),"Missing"),1,1)} -> 33970 | H419: {=IFERROR(_xlfn.XLOOKUP($A419,netflixPart2!$A:$A,_xlfn.CHOOSECOLS(netflixPart2!$A:$F,_xlfn.XMATCH(netflixPart1!H$1,netflixPart2!$A$1:$F$1))),"Missing")} -> TV-MA | I419: {=IFERROR(_xlfn.XLOOKUP($A419,netflixPart2!$A:$A,_xlfn.CHOOSECOLS(netflixPart2!$A:$F,_xlfn.XMATCH(netflixPart1!I$1,netflixPart2!$A$1:$F$1))),"Missing")} -> 124 min | J419: {=IFERROR(_xlfn.XLOOKUP($A419,netflixPart2!$A:$A,_xlfn.CHOOSECOLS(netflixPart2!$A:$F,_xlfn.XMATCH(netflixPart1!J$1,netflixPart2!$A$1:$F$1))),"Missing")} -> Classic Movies, Dramas, International Movies
A420: s4185 | B420: TV Show | C420: Trigger Warning with Killer Mike | D420: Not Given | E420: Pakistan | F420: {=IFERROR(_xlfn.XLOOKUP($A420,netflixPart2!$A:$A,_xlfn.CHOOSECOLS(netflixPart2!$A:$F,_xlfn.XMATCH(netflixPart1!F$1,netflixPart2!$A$1:$F$1))),"Missing")} -> 1/18/2019 | G420: {=DATE(IFERROR(_xlfn.XLOOKUP($A420,netflixPart2!$A:$A,_xlfn.CHOOSECOLS(netflixPart2!$A:$F,_xlfn.XMATCH(netflixPart1!G$1,netflixPart2!$A$1:$F$1))),"Missing"),1,1)} -> 43466 | H420: {=IFERROR(_xlfn.XLOOKUP($A420,netflixPart2!$A:$A,_xlfn.CHOOSECOLS(netflixPart2!$A:$F,_xlfn.XMATCH(netflixPart1!H$1,netflixPart2!$A$1:$F$1))),"Missing")} -> TV-MA | I420: {=IFERROR(_xlfn.XLOOKUP($A420,netflixPart2!$A:$A,_xlfn.CHOOSECOLS(netflixPart2!$A:$F,_xlfn.XMATCH(netflixPart1!I$1,netflixPart2!$A$1:$F$1))),"Missing")} -> 1 Season | J420: {=IFERROR(_xlfn.XLOOKUP($A420,netflixPart2!$A:$A,_xlfn.CHOOSECOLS(netflixPart2!$A:$F,_xlfn.XMATCH(netflixPart1!J$1,netflixPart2!$A$1:$F$1))),"Missing")} -> Docuseries, Stand-Up Comedy & Talk Shows
A421: s4200 | B421: TV Show | C421: Back with the Ex | D421: Not Given | E421: Pakistan | F421: {=IFERROR(_xlfn.XLOOKUP($A421,netflixPart2!$A:$A,_xlfn.CHOOSECOLS(netflixPart2!$A:$F,_xlfn.XMATCH(netflixPart1!F$1,netflixPart2!$A$1:$F$1))),"Missing")} -> 01/11/2019 | G421: {=DATE(IFERROR(_xlfn.XLOOKUP($A421,netflixPart2!$A:$A,_xlfn.CHOOSECOLS(netflixPart2!$A:$F,_xlfn.XMATCH(netflixPart1!G$1,netflixPart2!$A$1:$F$1))),"Missing"),1,1)} -> 43101 | H421: {=IFERROR(_xlfn.XLOOKUP($A421,netflixPart2!$A:$A,_xlfn.CHOOSECOLS(netflixPart2!$A:$F,_xlfn.XMATCH(netflixPart1!H$1,netflixPart2!$A$1:$F$1))),"Missing")} -> TV-MA | I421: {=IFERROR(_xlfn.XLOOKUP($A421,netflixPart2!$A:$A,_xlfn.CHOOSECOLS(netflixPart2!$A:$F,_xlfn.XMATCH(netflixPart1!I$1,netflixPart2!$A$1:$F$1))),"Missing")} -> 1 Season | J421: {=IFERROR(_xlfn.XLOOKUP($A421,netflixPart2!$A:$A,_xlfn.CHOOSECOLS(netflixPart2!$A:$F,_xlfn.XMATCH(netflixPart1!J$1,netflixPart2!$A$1:$F$1))),"Missing")} -> International TV Shows, Reality TV, Romantic TV Shows
A422: s4216 | B422: TV Show | C422: See You in Time | D422: Not Given | E422: Pakistan | F422: {=IFERROR(_xlfn.XLOOKUP($A422,netflixPart2!$A:$A,_xlfn.CHOOSECOLS(netflixPart2!$A:$F,_xlfn.XMATCH(netflixPart1!F$1,netflixPart2!$A$1:$F$1))),"Missing")} -> 01/04/2019 | G422: {=DATE(IFERROR(_xlfn.XLOOKUP($A422,netflixPart2!$A:$A,_xlfn.CHOOSECOLS(netflixPart2!$A:$F,_xlfn.XMATCH(netflixPart1!G$1,netflixPart2!$A$1:$F$1))),"Missing"),1,1)} -> 42736 | H422: {=IFERROR(_xlfn.XLOOKUP($A422,netflixPart2!$A:$A,_xlfn.CHOOSECOLS(netflixPart2!$A:$F,_xlfn.XMATCH(netflixPart1!H$1,netflixPart2!$A$1:$F$1))),"Missing")} -> TV-14 | I422: {=IFERROR(_xlfn.XLOOKUP($A422,netflixPart2!$A:$A,_xlfn.CHOOSECOLS(netflixPart2!$A:$F,_xlfn.XMATCH(netflixPart1!I$1,netflixPart2!$A$1:$F$1))),"Missing")} -> 1 Season | J422: {=IFERROR(_xlfn.XLOOKUP($A422,netflixPart2!$A:$A,_xlfn.CHOOSECOLS(netflixPart2!$A:$F,_xlfn.XMATCH(netflixPart1!J$1,netflixPart2!$A$1:$F$1))),"Missing")} -> International TV Shows, Romantic TV Shows, TV Dramas
A423: s4251 | B423: TV Show | C423: Pioneers: First Women Filmmakers* | D423: Not Given | E423: Pakistan | F423: {=IFERROR(_xlfn.XLOOKUP($A423,netflixPart2!$A:$A,_xlfn.CHOOSECOLS(netflixPart2!$A:$F,_xlfn.XMATCH(netflixPart1!F$1,netflixPart2!$A$1:$F$1))),"Missing")} -> 12/30/2018 | G423: {=DATE(IFERROR(_xlfn.XLOOKUP($A423,netflixPart2!$A:$A,_xlfn.CHOOSECOLS(netflixPart2!$A:$F,_xlfn.XMATCH(netflixPart1!G$1,netflixPart2!$A$1:$F$1))),"Missing"),1,1)} -> 9133 | H423: {=IFERROR(_xlfn.XLOOKUP($A423,netflixPart2!$A:$A,_xlfn.CHOOSECOLS(netflixPart2!$A:$F,_xlfn.XMATCH(netflixPart1!H$1,netflixPart2!$A$1:$F$1))),"Missing")} -> TV-14 | I423: {=IFERROR(_xlfn.XLOOKUP($A423,netflixPart2!$A:$A,_xlfn.CHOOSECOLS(netflixPart2!$A:$F,_xlfn.XMATCH(netflixPart1!I$1,netflixPart2!$A$1:$F$1))),"Missing")} -> 1 Season | J423: {=IFERROR(_xlfn.XLOOKUP($A423,netflixPart2!$A:$A,_xlfn.CHOOSECOLS(netflixPart2!$A:$F,_xlfn.XMATCH(netflixPart1!J$1,netflixPart2!$A$1:$F$1))),"Missing")} -> TV Shows
A424: s4231 | B424: Movie | C424: Bill Hicks: Reflections | D424: Not Given | E424: Pakistan | F424: {=IFERROR(_xlfn.XLOOKUP($A424,netflixPart2!$A:$A,_xlfn.CHOOSECOLS(netflixPart2!$A:$F,_xlfn.XMATCH(netflixPart1!F$1,netflixPart2!$A$1:$F$1))),"Missing")} -> 12/31/2018 | G424: {=DATE(IFERROR(_xlfn.XLOOKUP($A424,netflixPart2!$A:$A,_xlfn.CHOOSECOLS(netflixPart2!$A:$F,_xlfn.XMATCH(netflixPart1!G$1,netflixPart2!$A$1:$F$1))),"Missing"),1,1)} -> 42005 | H424: {=IFERROR(_xlfn.XLOOKUP($A424,netflixPart2!$A:$A,_xlfn.CHOOSECOLS(netflixPart2!$A:$F,_xlfn.XMATCH(netflixPart1!H$1,netflixPart2!$A$1:$F$1))),"Missing")} -> TV-MA | I424: {=IFERROR(_xlfn.XLOOKUP($A424,netflixPart2!$A:$A,_xlfn.CHOOSECOLS(netflixPart2!$A:$F,_xlfn.XMATCH(netflixPart1!I$1,netflixPart2!$A$1:$F$1))),"Missing")} -> 34 min | J424: {=IFERROR(_xlfn.XLOOKUP($A424,netflixPart2!$A:$A,_xlfn.CHOOSECOLS(netflixPart2!$A:$F,_xlfn.XMATCH(netflixPart1!J$1,netflixPart2!$A$1:$F$1))),"Missing")} -> Documentaries
A425: s4266 | B425: TV Show | C425: Single Ladies Senior | D425: Not Given | E425: Pakistan | F425: {=IFERROR(_xlfn.XLOOKUP($A425,netflixPart2!$A:$A,_xlfn.CHOOSECOLS(netflixPart2!$A:$F,_xlfn.XMATCH(netflixPart1!F$1,netflixPart2!$A$1:$F$1))),"Missing")} -> 12/22/2018 | G425: {=DATE(IFERROR(_xlfn.XLOOKUP($A425,netflixPart2!$A:$A,_xlfn.CHOOSECOLS(netflixPart2!$A:$F,_xlfn.XMATCH(netflixPart1!G$1,netflixPart2!$A$1:$F$1))),"Missing"),1,1)} -> 43101 | H425: {=IFERROR(_xlfn.XLOOKUP($A425,netflixPart2!$A:$A,_xlfn.CHOOSECOLS(netflixPart2!$A:$F,_xlfn.XMATCH(netflixPart1!H$1,netflixPart2!$A$1:$F$1))),"Missing")} -> TV-MA | I425: {=IFERROR(_xlfn.XLOOKUP($A425,netflixPart2!$A:$A,_xlfn.CHOOSECOLS(netflixPart2!$A:$F,_xlfn.XMATCH(netflixPart1!I$1,netflixPart2!$A$1:$F$1))),"Missing")} -> 1 Season | J425: {=IFERROR(_xlfn.XLOOKUP($A425,netflixPart2!$A:$A,_xlfn.CHOOSECOLS(netflixPart2!$A:$F,_xlfn.XMATCH(netflixPart1!J$1,netflixPart2!$A$1:$F$1))),"Missing")} -> International TV Shows, Romantic TV Shows, TV Dramas
A426: s4306 | B426: TV Show | C426: Inside the Real Narcos | D426: Not Given | E426: Pakistan | F426: {=IFERROR(_xlfn.XLOOKUP($A426,netflixPart2!$A:$A,_xlfn.CHOOSECOLS(netflixPart2!$A:$F,_xlfn.XMATCH(netflixPart1!F$1,netflixPart2!$A$1:$F$1))),"Missing")} -> 12/14/2018 | G426: {=DATE(IFERROR(_xlfn.XLOOKUP($A426,netflixPart2!$A:$A,_xlfn.CHOOSECOLS(netflixPart2!$A:$F,_xlfn.XMATCH(netflixPart1!G$1,netflixPart2!$A$1:$F$1))),"Missing"),1,1)} -> 43101 | H426: {=IFERROR(_xlfn.XLOOKUP($A426,netflixPart2!$A:$A,_xlfn.CHOOSECOLS(netflixPart2!$A:$F,_xlfn.XMATCH(netflixPart1!H$1,netflixPart2!$A$1:$F$1))),"Missing")} -> TV-MA | I426: {=IFERROR(_xlfn.XLOOKUP($A426,netflixPart2!$A:$A,_xlfn.CHOOSECOLS(netflixPart2!$A:$F,_xlfn.XMATCH(netflixPart1!I$1,netflixPart2!$A$1:$F$1))),"Missing")} -> 1 Season | J426: {=IFERROR(_xlfn.XLOOKUP($A426,netflixPart2!$A:$A,_xlfn.CHOOSECOLS(netflixPart2!$A:$F,_xlfn.XMATCH(netflixPart1!J$1,netflixPart2!$A$1:$F$1))),"Missing")} -> British TV Shows, Crime TV Shows, Docuseries
A427: s4341 | B427: TV Show | C427: Haunted House | D427: Not Given | E427: Pakistan | F427: {=IFERROR(_xlfn.XLOOKUP($A427,netflixPart2!$A:$A,_xlfn.CHOOSECOLS(netflixPart2!$A:$F,_xlfn.XMATCH(netflixPart1!F$1,netflixPart2!$A$1:$F$1))),"Missing")} -> 12/01/2018 | G427: {=DATE(IFERROR(_xlfn.XLOOKUP($A427,netflixPart2!$A:$A,_xlfn.CHOOSECOLS(netflixPart2!$A:$F,_xlfn.XMATCH(netflixPart1!G$1,netflixPart2!$A$1:$F$1))),"Missing"),1,1)} -> 42736 | H427: {=IFERROR(_xlfn.XLOOKUP($A427,netflixPart2!$A:$A,_xlfn.CHOOSECOLS(netflixPart2!$A:$F,_xlfn.XMATCH(netflixPart1!H$1,netflixPart2!$A$1:$F$1))),"Missing")} -> TV-G | I427: {=IFERROR(_xlfn.XLOOKUP($A427,netflixPart2!$A:$A,_xlfn.CHOOSECOLS(netflixPart2!$A:$F,_xlfn.XMATCH(netflixPart1!I$1,netflixPart2!$A$1:$F$1))),"Missing")} -> 1 Season | J427: {=IFERROR(_xlfn.XLOOKUP($A427,netflixPart2!$A:$A,_xlfn.CHOOSECOLS(netflixPart2!$A:$F,_xlfn.XMATCH(netflixPart1!J$1,netflixPart2!$A$1:$F$1))),"Missing")} -> Kids' TV, Korean TV Shows
A428: s4345 | B428: Movie | C428: Oddbods: The Festive Menace | D428: Not Given | E428: Pakistan | F428: {=IFERROR(_xlfn.XLOOKUP($A428,netflixPart2!$A:$A,_xlfn.CHOOSECOLS(netflixPart2!$A:$F,_xlfn.XMATCH(netflixPart1!F$1,netflixPart2!$A$1:$F$1))),"Missing")} -> 12/01/2018 | G428: {=DATE(IFERROR(_xlfn.XLOOKUP($A428,netflixPart2!$A:$A,_xlfn.CHOOSECOLS(netflixPart2!$A:$F,_xlfn.XMATCH(netflixPart1!G$1,netflixPart2!$A$1:$F$1))),"Missing"),1,1)} -> 43101 | H428: {=IFERROR(_xlfn.XLOOKUP($A428,netflixPart2!$A:$A,_xlfn.CHOOSECOLS(netflixPart2!$A:$F,_xlfn.XMATCH(netflixPart1!H$1,netflixPart2!$A$1:$F$1))),"Missing")} -> TV-Y | I428: {=IFERROR(_xlfn.XLOOKUP($A428,netflixPart2!$A:$A,_xlfn.CHOOSECOLS(netflixPart2!$A:$F,_xlfn.XMATCH(netflixPart1!I$1,netflixPart2!$A$1:$F$1))),"Missing")} -> 23 min | J428: {=IFERROR(_xlfn.XLOOKUP($A428,netflixPart2!$A:$A,_xlfn.CHOOSECOLS(netflixPart2!$A:$F,_xlfn.XMATCH(netflixPart1!J$1,netflixPart2!$A$1:$F$1))),"Missing")} -> Movies
A429: s4372 | B429: TV Show | C429: Kulipari: Dream Walker | D429: Not Given | E429: Pakistan | F429: {=IFERROR(_xlfn.XLOOKUP($A429,netflixPart2!$A:$A,_xlfn.CHOOSECOLS(netflixPart2!$A:$F,_xlfn.XMATCH(netflixPart1!F$1,netflixPart2!$A$1:$F$1))),"Missing")} -> 11/20/2018 | G429: {=DATE(IFERROR(_xlfn.XLOOKUP($A429,netflixPart2!$A:$A,_xlfn.CHOOSECOLS(netflixPart2!$A:$F,_xlfn.XMATCH(netflixPart1!G$1,netflixPart2!$A$1:$F$1))),"Missing"),1,1)} -> 43101 | H429: {=IFERROR(_xlfn.XLOOKUP($A429,netflixPart2!$A:$A,_xlfn.CHOOSECOLS(netflixPart2!$A:$F,_xlfn.XMATCH(netflixPart1!H$1,netflixPart2!$A$1:$F$1))),"Missing")} -> TV-Y7 | I429: {=IFERROR(_xlfn.XLOOKUP($A429,netflixPart2!$A:$A,_xlfn.CHOOSECOLS(netflixPart2!$A:$F,_xlfn.XMATCH(netflixPart1!I$1,netflixPart2!$A$1:$F$1))),"Missing")} -> 1 Season | J429: {=IFERROR(_xlfn.XLOOKUP($A429,netflixPart2!$A:$A,_xlfn.CHOOSECOLS(netflixPart2!$A:$F,_xlfn.XMATCH(netflixPart1!J$1,netflixPart2!$A$1:$F$1))),"Missing")} -> Kids' TV
... A538: s399 | B538: Movie | C538: Kingdom: Ashin of the North | D538: Kim Seong-hun | E538: South Korea | F538: {=IFERROR(_xlfn.XLOOKUP($A538,netflixPart2!$A:$A,_xlfn.CHOOSECOLS(netflixPart2!$A:$F,_xlfn.XMATCH(netflixPart1!F$1,netflixPart2!$A$1:$F$1))),"Missing")} -> 7/23/2021 | G538: {=DATE(IFERROR(_xlfn.XLOOKUP($A538,netflixPart2!$A:$A,_xlfn.CHOOSECOLS(netflixPart2!$A:$F,_xlfn.XMATCH(netflixPart1!G$1,netflixPart2!$A$1:$F$1))),"Missing"),1,1)} -> 44197 | H538: {=IFERROR(_xlfn.XLOOKUP($A538,netflixPart2!$A:$A,_xlfn.CHOOSECOLS(netflixPart2!$A:$F,_xlfn.XMATCH(netflixPart1!H$1,netflixPart2!$A$1:$F$1))),"Missing")} -> TV-MA | I538: {=IFERROR(_xlfn.XLOOKUP($A538,netflixPart2!$A:$A,_xlfn.CHOOSECOLS(netflixPart2!$A:$F,_xlfn.XMATCH(netflixPart1!I$1,netflixPart2!$A$1:$F$1))),"Missing")} -> 94 min | J538: {=IFERROR(_xlfn.XLOOKUP($A538,netflixPart2!$A:$A,_xlfn.CHOOSECOLS(netflixPart2!$A:$F,_xlfn.XMATCH(netflixPart1!J$1,netflixPart2!$A$1:$F$1))),"Missing")} -> Horror Movies, International Movies, Thrillers
A539: s5965 | B539: TV Show | C539: 09-Feb | D539: Not Given | E539: Pakistan | F539: {=IFERROR(_xlfn.XLOOKUP($A539,netflixPart2!$A:$A,_xlfn.CHOOSECOLS(netflixPart2!$A:$F,_xlfn.XMATCH(netflixPart1!F$1,netflixPart2!$A$1:$F$1))),"Missing")} -> 3/20/2019 | G539: {=DATE(IFERROR(_xlfn.XLOOKUP($A539,netflixPart2!$A:$A,_xlfn.CHOOSECOLS(netflixPart2!$A:$F,_xlfn.XMATCH(netflixPart1!G$1,netflixPart2!$A$1:$F$1))),"Missing"),1,1)} -> 43101 | H539: {=IFERROR(_xlfn.XLOOKUP($A539,netflixPart2!$A:$A,_xlfn.CHOOSECOLS(netflixPart2!$A:$F,_xlfn.XMATCH(netflixPart1!H$1,netflixPart2!$A$1:$F$1))),"Missing")} -> TV-14 | I539: {=IFERROR(_xlfn.XLOOKUP($A539,netflixPart2!$A:$A,_xlfn.CHOOSECOLS(netflixPart2!$A:$F,_xlfn.XMATCH(netflixPart1!I$1,netflixPart2!$A$1:$F$1))),"Missing")} -> 1 Season | J539: {=IFERROR(_xlfn.XLOOKUP($A539,netflixPart2!$A:$A,_xlfn.CHOOSECOLS(netflixPart2!$A:$F,_xlfn.XMATCH(netflixPart1!J$1,netflixPart2!$A$1:$F$1))),"Missing")} -> International TV Shows, TV Dramas | K539: =_xlfn.TEXTJOIN("|",FALSE,B539:J539) -> TV Show|09-Feb|Not Given|Pakistan|3/20/2019|43101|TV-14|1 Season|International TV Shows, TV Dramas
A540: s390 | B540: Movie | C540: The Operative | D540: Yuval Adler | E540: France | F540: {=IFERROR(_xlfn.XLOOKUP($A540,netflixPart2!$A:$A,_xlfn.CHOOSECOLS(netflixPart2!$A:$F,_xlfn.XMATCH(netflixPart1!F$1,netflixPart2!$A$1:$F$1))),"Missing")} -> 7/27/2021 | G540: {=DATE(IFERROR(_xlfn.XLOOKUP($A540,netflixPart2!$A:$A,_xlfn.CHOOSECOLS(netflixPart2!$A:$F,_xlfn.XMATCH(netflixPart1!G$1,netflixPart2!$A$1:$F$1))),"Missing"),1,1)} -> 43466 | H540: {=IFERROR(_xlfn.XLOOKUP($A540,netflixPart2!$A:$A,_xlfn.CHOOSECOLS(netflixPart2!$A:$F,_xlfn.XMATCH(netflixPart1!H$1,netflixPart2!$A$1:$F$1))),"Missing")} -> TV-MA | I540: {=IFERROR(_xlfn.XLOOKUP($A540,netflixPart2!$A:$A,_xlfn.CHOOSECOLS(netflixPart2!$A:$F,_xlfn.XMATCH(netflixPart1!I$1,netflixPart2!$A$1:$F$1))),"Missing")} -> 117 min | J540: {=IFERROR(_xlfn.XLOOKUP($A540,netflixPart2!$A:$A,_xlfn.CHOOSECOLS(netflixPart2!$A:$F,_xlfn.XMATCH(netflixPart1!J$1,netflixPart2!$A$1:$F$1))),"Missing")} -> Dramas, International Movies, Thrillers
A541: s5975 | B541: TV Show | C541: แผนร้ายนายเจ้าเล่ห์ | D541: Not Given | E541: Pakistan | F541: {=IFERROR(_xlfn.XLOOKUP($A541,netflixPart2!$A:$A,_xlfn.CHOOSECOLS(netflixPart2!$A:$F,_xlfn.XMATCH(netflixPart1!F$1,netflixPart2!$A$1:$F$1))),"Missing")} -> 3/30/2019 | G541: {=DATE(IFERROR(_xlfn.XLOOKUP($A541,netflixPart2!$A:$A,_xlfn.CHOOSECOLS(netflixPart2!$A:$F,_xlfn.XMATCH(netflixPart1!G$1,netflixPart2!$A$1:$F$1))),"Missing"),1,1)} -> 42370 | H541: {=IFERROR(_xlfn.XLOOKUP($A541,netflixPart2!$A:$A,_xlfn.CHOOSECOLS(netflixPart2!$A:$F,_xlfn.XMATCH(netflixPart1!H$1,netflixPart2!$A$1:$F$1))),"Missing")} -> TV-14 | I541: {=IFERROR(_xlfn.XLOOKUP($A541,netflixPart2!$A:$A,_xlfn.CHOOSECOLS(netflixPart2!$A:$F,_xlfn.XMATCH(netflixPart1!I$1,netflixPart2!$A$1:$F$1))),"Missing")} -> 1 Season | J541: {=IFERROR(_xlfn.XLOOKUP($A541,netflixPart2!$A:$A,_xlfn.CHOOSECOLS(netflixPart2!$A:$F,_xlfn.XMATCH(netflixPart1!J$1,netflixPart2!$A$1:$F$1))),"Missing")} -> International TV Shows, Romantic TV Shows, TV Comedies
A542: s393 | B542: Movie | C542: Django Unchained | D542: Quentin Tarantino | E542: United States | F542: {=IFERROR(_xlfn.XLOOKUP($A542,netflixPart2!$A:$A,_xlfn.CHOOSECOLS(netflixPart2!$A:$F,_xlfn.XMATCH(netflixPart1!F$1,netflixPart2!$A$1:$F$1))),"Missing")} -> 7/24/2021 | G542: {=DATE(IFERROR(_xlfn.XLOOKUP($A542,netflixPart2!$A:$A,_xlfn.CHOOSECOLS(netflixPart2!$A:$F,_xlfn.XMATCH(netflixPart1!G$1,netflixPart2!$A$1:$F$1))),"Missing"),1,1)} -> 40909 | H542: {=IFERROR(_xlfn.XLOOKUP($A542,netflixPart2!$A:$A,_xlfn.CHOOSECOLS(netflixPart2!$A:$F,_xlfn.XMATCH(netflixPart1!H$1,netflixPart2!$A$1:$F$1))),"Missing")} -> R | I542: {=IFERROR(_xlfn.XLOOKUP($A542,netflixPart2!$A:$A,_xlfn.CHOOSECOLS(netflixPart2!$A:$F,_xlfn.XMATCH(netflixPart1!I$1,netflixPart2!$A$1:$F$1))),"Missing")} -> 165 min | J542: {=IFERROR(_xlfn.XLOOKUP($A542,netflixPart2!$A:$A,_xlfn.CHOOSECOLS(netflixPart2!$A:$F,_xlfn.XMATCH(netflixPart1!J$1,netflixPart2!$A$1:$F$1))),"Missing")} -> Action & Adventure, Dramas
A543: s394 | B543: Movie | C543: A Second Chance: Rivals! | D543: Clay Glen | E543: Australia | F543: {=IFERROR(_xlfn.XLOOKUP($A543,netflixPart2!$A:$A,_xlfn.CHOOSECOLS(netflixPart2!$A:$F,_xlfn.XMATCH(netflixPart1!F$1,netflixPart2!$A$1:$F$1))),"Missing")} -> 7/23/2021 | G543: {=DATE(IFERROR(_xlfn.XLOOKUP($A543,netflixPart2!$A:$A,_xlfn.CHOOSECOLS(netflixPart2!$A:$F,_xlfn.XMATCH(netflixPart1!G$1,netflixPart2!$A$1:$F$1))),"Missing"),1,1)} -> 44197 | H543: {=IFERROR(_xlfn.XLOOKUP($A543,netflixPart2!$A:$A,_xlfn.CHOOSECOLS(netflixPart2!$A:$F,_xlfn.XMATCH(netflixPart1!H$1,netflixPart2!$A$1:$F$1))),"Missing")} -> PG | I543: {=IFERROR(_xlfn.XLOOKUP($A543,netflixPart2!$A:$A,_xlfn.CHOOSECOLS(netflixPart2!$A:$F,_xlfn.XMATCH(netflixPart1!I$1,netflixPart2!$A$1:$F$1))),"Missing")} -> 91 min | J543: {=IFERROR(_xlfn.XLOOKUP($A543,netflixPart2!$A:$A,_xlfn.CHOOSECOLS(netflixPart2!$A:$F,_xlfn.XMATCH(netflixPart1!J$1,netflixPart2!$A$1:$F$1))),"Missing")} -> Children & Family Movies, Sports Movies
A544: s6266 | B544: TV Show | C544: Beauty and the Bitches | D544: Not Given | E544: Pakistan | F544: {=IFERROR(_xlfn.XLOOKUP($A544,netflixPart2!$A:$A,_xlfn.CHOOSECOLS(netflixPart2!$A:$F,_xlfn.XMATCH(netflixPart1!F$1,netflixPart2!$A$1:$F$1))),"Missing")} -> 4/23/2019 | G544: {=DATE(IFERROR(_xlfn.XLOOKUP($A544,netflixPart2!$A:$A,_xlfn.CHOOSECOLS(netflixPart2!$A:$F,_xlfn.XMATCH(netflixPart1!G$1,netflixPart2!$A$1:$F$1))),"Missing"),1,1)} -> 42370 | H544: {=IFERROR(_xlfn.XLOOKUP($A544,netflixPart2!$A:$A,_xlfn.CHOOSECOLS(netflixPart2!$A:$F,_xlfn.XMATCH(netflixPart1!H$1,netflixPart2!$A$1:$F$1))),"Missing")} -> TV-MA | I544: {=IFERROR(_xlfn.XLOOKUP($A544,netflixPart2!$A:$A,_xlfn.CHOOSECOLS(netflixPart2!$A:$F,_xlfn.XMATCH(netflixPart1!I$1,netflixPart2!$A$1:$F$1))),"Missing")} -> 2 Seasons | J544: {=IFERROR(_xlfn.XLOOKUP($A544,netflixPart2!$A:$A,_xlfn.CHOOSECOLS(netflixPart2!$A:$F,_xlfn.XMATCH(netflixPart1!J$1,netflixPart2!$A$1:$F$1))),"Missing")} -> International TV Shows, Romantic TV Shows, TV Comedies
A545: s6276 | B545: TV Show | C545: Behind the Newsroom | D545: Not Given | E545: Pakistan | F545: {=IFERROR(_xlfn.XLOOKUP($A545,netflixPart2!$A:$A,_xlfn.CHOOSECOLS(netflixPart2!$A:$F,_xlfn.XMATCH(netflixPart1!F$1,netflixPart2!$A$1:$F$1))),"Missing")} -> 9/14/2018 | G545: {=DATE(IFERROR(_xlfn.XLOOKUP($A545,netflixPart2!$A:$A,_xlfn.CHOOSECOLS(netflixPart2!$A:$F,_xlfn.XMATCH(netflixPart1!G$1,netflixPart2!$A$1:$F$1))),"Missing"),1,1)} -> 42005 | H545: {=IFERROR(_xlfn.XLOOKUP($A545,netflixPart2!$A:$A,_xlfn.CHOOSECOLS(netflixPart2!$A:$F,_xlfn.XMATCH(netflixPart1!H$1,netflixPart2!$A$1:$F$1))),"Missing")} -> TV-MA | I545: {=IFERROR(_xlfn.XLOOKUP($A545,netflixPart2!$A:$A,_xlfn.CHOOSECOLS(netflixPart2!$A:$F,_xlfn.XMATCH(netflixPart1!I$1,netflixPart2!$A$1:$F$1))),"Missing")} -> 1 Season | J545: {=IFERROR(_xlfn.XLOOKUP($A545,netflixPart2!$A:$A,_xlfn.CHOOSECOLS(netflixPart2!$A:$F,_xlfn.XMATCH(netflixPart1!J$1,netflixPart2!$A$1:$F$1))),"Missing")} -> International TV Shows, Romantic TV Shows, TV Dramas
A546: s6348 | B546: TV Show | C546: Bob Ross: Beauty Is Everywhere | D546: Not Given | E546: Pakistan | F546: {=IFERROR(_xlfn.XLOOKUP($A546,netflixPart2!$A:$A,_xlfn.CHOOSECOLS(netflixPart2!$A:$F,_xlfn.XMATCH(netflixPart1!F$1,netflixPart2!$A$1:$F$1))),"Missing")} -> 06/01/2016 | G546: {=DATE(IFERROR(_xlfn.XLOOKUP($A546,netflixPart2!$A:$A,_xlfn.CHOOSECOLS(netflixPart2!$A:$F,_xlfn.XMATCH(netflixPart1!G$1,netflixPart2!$A$1:$F$1))),"Missing"),1,1)} -> 33239 | H546: {=IFERROR(_xlfn.XLOOKUP($A546,netflixPart2!$A:$A,_xlfn.CHOOSECOLS(netflixPart2!$A:$F,_xlfn.XMATCH(netflixPart1!H$1,netflixPart2!$A$1:$F$1))),"Missing")} -> TV-G | I546: {=IFERROR(_xlfn.XLOOKUP($A546,netflixPart2!$A:$A,_xlfn.CHOOSECOLS(netflixPart2!$A:$F,_xlfn.XMATCH(netflixPart1!I$1,netflixPart2!$A$1:$F$1))),"Missing")} -> 1 Season | J546: {=IFERROR(_xlfn.XLOOKUP($A546,netflixPart2!$A:$A,_xlfn.CHOOSECOLS(netflixPart2!$A:$F,_xlfn.XMATCH(netflixPart1!J$1,netflixPart2!$A$1:$F$1))),"Missing")} -> TV Shows
A547: s6361 | B547: TV Show | C547: Border Patrol | D547: Not Given | E547: Pakistan | F547: {=IFERROR(_xlfn.XLOOKUP($A547,netflixPart2!$A:$A,_xlfn.CHOOSECOLS(netflixPart2!$A:$F,_xlfn.XMATCH(netflixPart1!F$1,netflixPart2!$A$1:$F$1))),"Missing")} -> 10/02/2019 | G547: {=DATE(IFERROR(_xlfn.XLOOKUP($A547,netflixPart2!$A:$A,_xlfn.CHOOSECOLS(netflixPart2!$A:$F,_xlfn.XMATCH(netflixPart1!G$1,netflixPart2!$A$1:$F$1))),"Missing"),1,1)} -> 42370 | H547: {=IFERROR(_xlfn.XLOOKUP($A547,netflixPart2!$A:$A,_xlfn.CHOOSECOLS(netflixPart2!$A:$F,_xlfn.XMATCH(netflixPart1!H$1,netflixPart2!$A$1:$F$1))),"Missing")} -> TV-PG | I547: {=IFERROR(_xlfn.XLOOKUP($A547,netflixPart2!$A:$A,_xlfn.CHOOSECOLS(netflixPart2!$A:$F,_xlfn.XMATCH(netflixPart1!I$1,netflixPart2!$A$1:$F$1))),"Missing")} -> 1 Season | J547: {=IFERROR(_xlfn.XLOOKUP($A547,netflixPart2!$A:$A,_xlfn.CHOOSECOLS(netflixPart2!$A:$F,_xlfn.XMATCH(netflixPart1!J$1,netflixPart2!$A$1:$F$1))),"Missing")} -> Reality TV
A548: s6379 | B548: TV Show | C548: Bringing Sexy Back | D548: Not Given | E548: Pakistan | F548: {=IFERROR(_xlfn.XLOOKUP($A548,netflixPart2!$A:$A,_xlfn.CHOOSECOLS(netflixPart2!$A:$F,_xlfn.XMATCH(netflixPart1!F$1,netflixPart2!$A$1:$F$1))),"Missing")} -> 10/02/2019 | G548: {=DATE(IFERROR(_xlfn.XLOOKUP($A548,netflixPart2!$A:$A,_xlfn.CHOOSECOLS(netflixPart2!$A:$F,_xlfn.XMATCH(netflixPart1!G$1,netflixPart2!$A$1:$F$1))),"Missing"),1,1)} -> 42005 | H548: {=IFERROR(_xlfn.XLOOKUP($A548,netflixPart2!$A:$A,_xlfn.CHOOSECOLS(netflixPart2!$A:$F,_xlfn.XMATCH(netflixPart1!H$1,netflixPart2!$A$1:$F$1))),"Missing")} -> TV-14 | I548: {=IFERROR(_xlfn.XLOOKUP($A548,netflixPart2!$A:$A,_xlfn.CHOOSECOLS(netflixPart2!$A:$F,_xlfn.XMATCH(netflixPart1!I$1,netflixPart2!$A$1:$F$1))),"Missing")} -> 1 Season | J548: {=IFERROR(_xlfn.XLOOKUP($A548,netflixPart2!$A:$A,_xlfn.CHOOSECOLS(netflixPart2!$A:$F,_xlfn.XMATCH(netflixPart1!J$1,netflixPart2!$A$1:$F$1))),"Missing")} -> International TV Shows, Reality TV
A549: s6386 | B549: TV Show | C549: Buddha | D549: Not Given | E549: Pakistan | F549: {=IFERROR(_xlfn.XLOOKUP($A549,netflixPart2!$A:$A,_xlfn.CHOOSECOLS(netflixPart2!$A:$F,_xlfn.XMATCH(netflixPart1!F$1,netflixPart2!$A$1:$F$1))),"Missing")} -> 04/01/2018 | G549: {=DATE(IFERROR(_xlfn.XLOOKUP($A549,netflixPart2!$A:$A,_xlfn.CHOOSECOLS(netflixPart2!$A:$F,_xlfn.XMATCH(netflixPart1!G$1,netflixPart2!$A$1:$F$1))),"Missing"),1,1)} -> 41275 | H549: {=IFERROR(_xlfn.XLOOKUP($A549,netflixPart2!$A:$A,_xlfn.CHOOSECOLS(netflixPart2!$A:$F,_xlfn.XMATCH(netflixPart1!H$1,netflixPart2!$A$1:$F$1))),"Missing")} -> TV-PG | I549: {=IFERROR(_xlfn.XLOOKUP($A549,netflixPart2!$A:$A,_xlfn.CHOOSECOLS(netflixPart2!$A:$F,_xlfn.XMATCH(netflixPart1!I$1,netflixPart2!$A$1:$F$1))),"Missing")} -> 1 Season | J549: {=IFERROR(_xlfn.XLOOKUP($A549,netflixPart2!$A:$A,_xlfn.CHOOSECOLS(netflixPart2!$A:$F,_xlfn.XMATCH(netflixPart1!J$1,netflixPart2!$A$1:$F$1))),"Missing")} -> International TV Shows, TV Dramas
A550: s6390 | B550: TV Show | C550: Bure Kaam Bura Natija, Kyun Bhai Chacha Haan Bhatija | D550: Not Given | E550: Pakistan | F550: {=IFERROR(_xlfn.XLOOKUP($A550,netflixPart2!$A:$A,_xlfn.CHOOSECOLS(netflixPart2!$A:$F,_xlfn.XMATCH(netflixPart1!F$1,netflixPart2!$A$1:$F$1))),"Missing")} -> 3/31/2018 | G550: {=DATE(IFERROR(_xlfn.XLOOKUP($A550,netflixPart2!$A:$A,_xlfn.CHOOSECOLS(netflixPart2!$A:$F,_xlfn.XMATCH(netflixPart1!G$1,netflixPart2!$A$1:$F$1))),"Missing"),1,1)} -> 42736 | H550: {=IFERROR(_xlfn.XLOOKUP($A550,netflixPart2!$A:$A,_xlfn.CHOOSECOLS(netflixPart2!$A:$F,_xlfn.XMATCH(netflixPart1!H$1,netflixPart2!$A$1:$F$1))),"Missing")} -> TV-PG | I550: {=IFERROR(_xlfn.XLOOKUP($A550,netflixPart2!$A:$A,_xlfn.CHOOSECOLS(netflixPart2!$A:$F,_xlfn.XMATCH(netflixPart1!I$1,netflixPart2!$A$1:$F$1))),"Missing")} -> 1 Season | J550: {=IFERROR(_xlfn.XLOOKUP($A550,netflixPart2!$A:$A,_xlfn.CHOOSECOLS(netflixPart2!$A:$F,_xlfn.XMATCH(netflixPart1!J$1,netflixPart2!$A$1:$F$1))),"Missing")} -> Kids' TV
A551: s6431 | B551: TV Show | C551: Castle of Stars | D551: Not Given | E551: Pakistan | F551: {=IFERROR(_xlfn.XLOOKUP($A551,netflixPart2!$A:$A,_xlfn.CHOOSECOLS(netflixPart2!$A:$F,_xlfn.XMATCH(netflixPart1!F$1,netflixPart2!$A$1:$F$1))),"Missing")} -> 09/07/2018 | G551: {=DATE(IFERROR(_xlfn.XLOOKUP($A551,netflixPart2!$A:$A,_xlfn.CHOOSECOLS(netflixPart2!$A:$F,_xlfn.XMATCH(netflixPart1!G$1,netflixPart2!$A$1:$F$1))),"Missing"),1,1)} -> 42005 | H551: {=IFERROR(_xlfn.XLOOKUP($A551,netflixPart2!$A:$A,_xlfn.CHOOSECOLS(netflixPart2!$A:$F,_xlfn.XMATCH(netflixPart1!H$1,netflixPart2!$A$1:$F$1))),"Missing")} -> TV-MA | I551: {=IFERROR(_xlfn.XLOOKUP($A551,netflixPart2!$A:$A,_xlfn.CHOOSECOLS(netflixPart2!$A:$F,_xlfn.XMATCH(netflixPart1!I$1,netflixPart2!$A$1:$F$1))),"Missing")} -> 1 Season | J551: {=IFERROR(_xlfn.XLOOKUP($A551,netflixPart2!$A:$A,_xlfn.CHOOSECOLS(netflixPart2!$A:$F,_xlfn.XMATCH(netflixPart1!J$1,netflixPart2!$A$1:$F$1))),"Missing")} -> International TV Shows, Romantic TV Shows, TV Comedies
... A2926: s3961 | B2926: Movie | C2926: The Burial of Kojo | D2926: Sam Blitz Bazawule | E2926: Ghana | F2926: {=IFERROR(_xlfn.XLOOKUP($A2926,netflixPart2!$A:$A,_xlfn.CHOOSECOLS(netflixPart2!$A:$F,_xlfn.XMATCH(netflixPart1!F$1,netflixPart2!$A$1:$F$1))),"Missing")} -> 3/31/2019 | G2926: {=DATE(IFERROR(_xlfn.XLOOKUP($A2926,netflixPart2!$A:$A,_xlfn.CHOOSECOLS(netflixPart2!$A:$F,_xlfn.XMATCH(netflixPart1!G$1,netflixPart2!$A$1:$F$1))),"Missing"),1,1)} -> 43101 | H2926: {=IFERROR(_xlfn.XLOOKUP($A2926,netflixPart2!$A:$A,_xlfn.CHOOSECOLS(netflixPart2!$A:$F,_xlfn.XMATCH(netflixPart1!H$1,netflixPart2!$A$1:$F$1))),"Missing")} -> TV-14 | I2926: {=IFERROR(_xlfn.XLOOKUP($A2926,netflixPart2!$A:$A,_xlfn.CHOOSECOLS(netflixPart2!$A:$F,_xlfn.XMATCH(netflixPart1!I$1,netflixPart2!$A$1:$F$1))),"Missing")} -> 81 min | J2926: {=IFERROR(_xlfn.XLOOKUP($A2926,netflixPart2!$A:$A,_xlfn.CHOOSECOLS(netflixPart2!$A:$F,_xlfn.XMATCH(netflixPart1!J$1,netflixPart2!$A$1:$F$1))),"Missing")} -> Dramas, Independent Movies, International Movies
A2927: s3963 | B2927: Movie | C2927: 15-Aug | D2927: Swapnaneel Jayakar | E2927: India | F2927: {=IFERROR(_xlfn.XLOOKUP($A2927,netflixPart2!$A:$A,_xlfn.CHOOSECOLS(netflixPart2!$A:$F,_xlfn.XMATCH(netflixPart1!F$1,netflixPart2!$A$1:$F$1))),"Missing")} -> 3/29/2019 | G2927: {=DATE(IFERROR(_xlfn.XLOOKUP($A2927,netflixPart2!$A:$A,_xlfn.CHOOSECOLS(netflixPart2!$A:$F,_xlfn.XMATCH(netflixPart1!G$1,netflixPart2!$A$1:$F$1))),"Missing"),1,1)} -> 43466 | H2927: {=IFERROR(_xlfn.XLOOKUP($A2927,netflixPart2!$A:$A,_xlfn.CHOOSECOLS(netflixPart2!$A:$F,_xlfn.XMATCH(netflixPart1!H$1,netflixPart2!$A$1:$F$1))),"Missing")} -> TV-14 | I2927: {=IFERROR(_xlfn.XLOOKUP($A2927,netflixPart2!$A:$A,_xlfn.CHOOSECOLS(netflixPart2!$A:$F,_xlfn.XMATCH(netflixPart1!I$1,netflixPart2!$A$1:$F$1))),"Missing")} -> 124 min | J2927: {=IFERROR(_xlfn.XLOOKUP($A2927,netflixPart2!$A:$A,_xlfn.CHOOSECOLS(netflixPart2!$A:$F,_xlfn.XMATCH(netflixPart1!J$1,netflixPart2!$A$1:$F$1))),"Missing")} -> Comedies, Dramas, Independent Movies | K2927: =_xlfn.TEXTJOIN("|",FALSE,B2927:J2927) -> Movie|15-Aug|Swapnaneel Jayakar|India|3/29/2019|43466|TV-14|124 min|Comedies, Dramas, Independent Movies
A2928: s3964 | B2928: Movie | C2928: Bayonet | D2928: Kyzza Terrazas | E2928: Mexico | F2928: {=IFERROR(_xlfn.XLOOKUP($A2928,netflixPart2!$A:$A,_xlfn.CHOOSECOLS(netflixPart2!$A:$F,_xlfn.XMATCH(netflixPart1!F$1,netflixPart2!$A$1:$F$1))),"Missing")} -> 3/29/2019 | G2928: {=DATE(IFERROR(_xlfn.XLOOKUP($A2928,netflixPart2!$A:$A,_xlfn.CHOOSECOLS(netflixPart2!$A:$F,_xlfn.XMATCH(netflixPart1!G$1,netflixPart2!$A$1:$F$1))),"Missing"),1,1)} -> 43466 | H2928: {=IFERROR(_xlfn.XLOOKUP($A2928,netflixPart2!$A:$A,_xlfn.CHOOSECOLS(netflixPart2!$A:$F,_xlfn.XMATCH(netflixPart1!H$1,netflixPart2!$A$1:$F$1))),"Missing")} -> TV-MA | I2928: {=IFERROR(_xlfn.XLOOKUP($A2928,netflixPart2!$A:$A,_xlfn.CHOOSECOLS(netflixPart2!$A:$F,_xlfn.XMATCH(netflixPart1!I$1,netflixPart2!$A$1:$F$1))),"Missing")} -> 102 min | J2928: {=IFERROR(_xlfn.XLOOKUP($A2928,netflixPart2!$A:$A,_xlfn.CHOOSECOLS(netflixPart2!$A:$F,_xlfn.XMATCH(netflixPart1!J$1,netflixPart2!$A$1:$F$1))),"Missing")} -> Dramas, International Movies, Sports Movies
A2929: s3967 | B2929: Movie | C2929: The Highwaymen | D2929: John Lee Hancock | E2929: United States | F2929: {=IFERROR(_xlfn.XLOOKUP($A2929,netflixPart2!$A:$A,_xlfn.CHOOSECOLS(netflixPart2!$A:$F,_xlfn.XMATCH(netflixPart1!F$1,netflixPart2!$A$1:$F$1))),"Missing")} -> 3/29/2019 | G2929: {=DATE(IFERROR(_xlfn.XLOOKUP($A2929,netflixPart2!$A:$A,_xlfn.CHOOSECOLS(netflixPart2!$A:$F,_xlfn.XMATCH(netflixPart1!G$1,netflixPart2!$A$1:$F$1))),"Missing"),1,1)} -> 43466 | H2929: {=IFERROR(_xlfn.XLOOKUP($A2929,netflixPart2!$A:$A,_xlfn.CHOOSECOLS(netflixPart2!$A:$F,_xlfn.XMATCH(netflixPart1!H$1,netflixPart2!$A$1:$F$1))),"Missing")} -> R | I2929: {=IFERROR(_xlfn.XLOOKUP($A2929,netflixPart2!$A:$A,_xlfn.CHOOSECOLS(netflixPart2!$A:$F,_xlfn.XMATCH(netflixPart1!I$1,netflixPart2!$A$1:$F$1))),"Missing")} -> 132 min | J2929: {=IFERROR(_xlfn.XLOOKUP($A2929,netflixPart2!$A:$A,_xlfn.CHOOSECOLS(netflixPart2!$A:$F,_xlfn.XMATCH(netflixPart1!J$1,netflixPart2!$A$1:$F$1))),"Missing")} -> Dramas
A2930: s3968 | B2930: Movie | C2930: The Legend of Cocaine Island | D2930: Theo Love | E2930: United States | F2930: {=IFERROR(_xlfn.XLOOKUP($A2930,netflixPart2!$A:$A,_xlfn.CHOOSECOLS(netflixPart2!$A:$F,_xlfn.XMATCH(netflixPart1!F$1,netflixPart2!$A$1:$F$1))),"Missing")} -> 3/29/2019 | G2930: {=DATE(IFERROR(_xlfn.XLOOKUP($A2930,netflixPart2!$A:$A,_xlfn.CHOOSECOLS(netflixPart2!$A:$F,_xlfn.XMATCH(netflixPart1!G$1,netflixPart2!$A$1:$F$1))),"Missing"),1,1)} -> 43466 | H2930: {=IFERROR(_xlfn.XLOOKUP($A2930,netflixPart2!$A:$A,_xlfn.CHOOSECOLS(netflixPart2!$A:$F,_xlfn.XMATCH(netflixPart1!H$1,netflixPart2!$A$1:$F$1))),"Missing")} -> TV-MA | I2930: {=IFERROR(_xlfn.XLOOKUP($A2930,netflixPart2!$A:$A,_xlfn.CHOOSECOLS(netflixPart2!$A:$F,_xlfn.XMATCH(netflixPart1!I$1,netflixPart2!$A$1:$F$1))),"Missing")} -> 87 min | J2930: {=IFERROR(_xlfn.XLOOKUP($A2930,netflixPart2!$A:$A,_xlfn.CHOOSECOLS(netflixPart2!$A:$F,_xlfn.XMATCH(netflixPart1!J$1,netflixPart2!$A$1:$F$1))),"Missing")} -> Documentaries
A2931: s3973 | B2931: Movie | C2931: Danur: I Can See Ghosts | D2931: Awi Suryadi | E2931: Indonesia | F2931: {=IFERROR(_xlfn.XLOOKUP($A2931,netflixPart2!$A:$A,_xlfn.CHOOSECOLS(netflixPart2!$A:$F,_xlfn.XMATCH(netflixPart1!F$1,netflixPart2!$A$1:$F$1))),"Missing")} -> 3/27/2019 | G2931: {=DATE(IFERROR(_xlfn.XLOOKUP($A2931,netflixPart2!$A:$A,_xlfn.CHOOSECOLS(netflixPart2!$A:$F,_xlfn.XMATCH(netflixPart1!G$1,netflixPart2!$A$1:$F$1))),"Missing"),1,1)} -> 42736 | H2931: {=IFERROR(_xlfn.XLOOKUP($A2931,netflixPart2!$A:$A,_xlfn.CHOOSECOLS(netflixPart2!$A:$F,_xlfn.XMATCH(netflixPart1!H$1,netflixPart2!$A$1:$F$1))),"Missing")} -> TV-MA | I2931: {=IFERROR(_xlfn.XLOOKUP($A2931,netflixPart2!$A:$A,_xlfn.CHOOSECOLS(netflixPart2!$A:$F,_xlfn.XMATCH(netflixPart1!I$1,netflixPart2!$A$1:$F$1))),"Missing")} -> 75 min | J2931: {=IFERROR(_xlfn.XLOOKUP($A2931,netflixPart2!$A:$A,_xlfn.CHOOSECOLS(netflixPart2!$A:$F,_xlfn.XMATCH(netflixPart1!J$1,netflixPart2!$A$1:$F$1))),"Missing")} -> Horror Movies, International Movies
A2932: s3974 | B2932: Movie | C2932: Verses of Love | D2932: Hanung Bramantyo | E2932: Indonesia | F2932: {=IFERROR(_xlfn.XLOOKUP($A2932,netflixPart2!$A:$A,_xlfn.CHOOSECOLS(netflixPart2!$A:$F,_xlfn.XMATCH(netflixPart1!F$1,netflixPart2!$A$1:$F$1))),"Missing")} -> 3/27/2019 | G2932: {=DATE(IFERROR(_xlfn.XLOOKUP($A2932,netflixPart2!$A:$A,_xlfn.CHOOSECOLS(netflixPart2!$A:$F,_xlfn.XMATCH(netflixPart1!G$1,netflixPart2!$A$1:$F$1))),"Missing"),1,1)} -> 39448 | H2932: {=IFERROR(_xlfn.XLOOKUP($A2932,netflixPart2!$A:$A,_xlfn.CHOOSECOLS(netflixPart2!$A:$F,_xlfn.XMATCH(netflixPart1!H$1,netflixPart2!$A$1:$F$1))),"Missing")} -> TV-PG | I2932: {=IFERROR(_xlfn.XLOOKUP($A2932,netflixPart2!$A:$A,_xlfn.CHOOSECOLS(netflixPart2!$A:$F,_xlfn.XMATCH(netflixPart1!I$1,netflixPart2!$A$1:$F$1))),"Missing")} -> 126 min | J2932: {=IFERROR(_xlfn.XLOOKUP($A2932,netflixPart2!$A:$A,_xlfn.CHOOSECOLS(netflixPart2!$A:$F,_xlfn.XMATCH(netflixPart1!J$1,netflixPart2!$A$1:$F$1))),"Missing")} -> Dramas, International Movies, Romantic Movies
A2933: s3975 | B2933: Movie | C2933: Nate Bargatze: The Tennessee Kid | D2933: Ryan Polito | E2933: United States | F2933: {=IFERROR(_xlfn.XLOOKUP($A2933,netflixPart2!$A:$A,_xlfn.CHOOSECOLS(netflixPart2!$A:$F,_xlfn.XMATCH(netflixPart1!F$1,netflixPart2!$A$1:$F$1))),"Missing")} -> 3/26/2019 | G2933: {=DATE(IFERROR(_xlfn.XLOOKUP($A2933,netflixPart2!$A:$A,_xlfn.CHOOSECOLS(netflixPart2!$A:$F,_xlfn.XMATCH(netflixPart1!G$1,netflixPart2!$A$1:$F$1))),"Missing"),1,1)} -> 43466 | H2933: {=IFERROR(_xlfn.XLOOKUP($A2933,netflixPart2!$A:$A,_xlfn.CHOOSECOLS(netflixPart2!$A:$F,_xlfn.XMATCH(netflixPart1!H$1,netflixPart2!$A$1:$F$1))),"Missing")} -> TV-PG | I2933: {=IFERROR(_xlfn.XLOOKUP($A2933,netflixPart2!$A:$A,_xlfn.CHOOSECOLS(netflixPart2!$A:$F,_xlfn.XMATCH(netflixPart1!I$1,netflixPart2!$A$1:$F$1))),"Missing")} -> 61 min | J2933: {=IFERROR(_xlfn.XLOOKUP($A2933,netflixPart2!$A:$A,_xlfn.CHOOSECOLS(netflixPart2!$A:$F,_xlfn.XMATCH(netflixPart1!J$1,netflixPart2!$A$1:$F$1))),"Missing")} -> Stand-Up Comedy
A2934: s3976 | B2934: Movie | C2934: Sei | D2934: Raj Babu | E2934: India | F2934: {=IFERROR(_xlfn.XLOOKUP($A2934,netflixPart2!$A:$A,_xlfn.CHOOSECOLS(netflixPart2!$A:$F,_xlfn.XMATCH(netflixPart1!F$1,netflixPart2!$A$1:$F$1))),"Missing")} -> 3/25/2019 | G2934: {=DATE(IFERROR(_xlfn.XLOOKUP($A2934,netflixPart2!$A:$A,_xlfn.CHOOSECOLS(netflixPart2!$A:$F,_xlfn.XMATCH(netflixPart1!G$1,netflixPart2!$A$1:$F$1))),"Missing"),1,1)} -> 43101 | H2934: {=IFERROR(_xlfn.XLOOKUP($A2934,netflixPart2!$A:$A,_xlfn.CHOOSECOLS(netflixPart2!$A:$F,_xlfn.XMATCH(netflixPart1!H$1,netflixPart2!$A$1:$F$1))),"Missing")} -> TV-14 | I2934: {=IFERROR(_xlfn.XLOOKUP($A2934,netflixPart2!$A:$A,_xlfn.CHOOSECOLS(netflixPart2!$A:$F,_xlfn.XMATCH(netflixPart1!I$1,netflixPart2!$A$1:$F$1))),"Missing")} -> 126 min | J2934: {=IFERROR(_xlfn.XLOOKUP($A2934,netflixPart2!$A:$A,_xlfn.CHOOSECOLS(netflixPart2!$A:$F,_xlfn.XMATCH(netflixPart1!J$1,netflixPart2!$A$1:$F$1))),"Missing")} -> Action & Adventure, Comedies, Dramas
A2935: s3978 | B2935: Movie | C2935: Superlopez | D2935: Javier Ruiz Caldera | E2935: Spain | F2935: {=IFERROR(_xlfn.XLOOKUP($A2935,netflixPart2!$A:$A,_xlfn.CHOOSECOLS(netflixPart2!$A:$F,_xlfn.XMATCH(netflixPart1!F$1,netflixPart2!$A$1:$F$1))),"Missing")} -> 3/24/2019 | G2935: {=DATE(IFERROR(_xlfn.XLOOKUP($A2935,netflixPart2!$A:$A,_xlfn.CHOOSECOLS(netflixPart2!$A:$F,_xlfn.XMATCH(netflixPart1!G$1,netflixPart2!$A$1:$F$1))),"Missing"),1,1)} -> 43101 | H2935: {=IFERROR(_xlfn.XLOOKUP($A2935,netflixPart2!$A:$A,_xlfn.CHOOSECOLS(netflixPart2!$A:$F,_xlfn.XMATCH(netflixPart1!H$1,netflixPart2!$A$1:$F$1))),"Missing")} -> TV-MA | I2935: {=IFERROR(_xlfn.XLOOKUP($A2935,netflixPart2!$A:$A,_xlfn.CHOOSECOLS(netflixPart2!$A:$F,_xlfn.XMATCH(netflixPart1!I$1,netflixPart2!$A$1:$F$1))),"Missing")} -> 108 min | J2935: {=IFERROR(_xlfn.XLOOKUP($A2935,netflixPart2!$A:$A,_xlfn.CHOOSECOLS(netflixPart2!$A:$F,_xlfn.XMATCH(netflixPart1!J$1,netflixPart2!$A$1:$F$1))),"Missing")} -> Action & Adventure, Comedies, International Movies
A2936: s3979 | B2936: Movie | C2936: Oversize Cops | D2936: Chanon Yingyong, Phuwanit Pholdee | E2936: Thailand | F2936: {=IFERROR(_xlfn.XLOOKUP($A2936,netflixPart2!$A:$A,_xlfn.CHOOSECOLS(netflixPart2!$A:$F,_xlfn.XMATCH(netflixPart1!F$1,netflixPart2!$A$1:$F$1))),"Missing")} -> 3/23/2019 | G2936: {=DATE(IFERROR(_xlfn.XLOOKUP($A2936,netflixPart2!$A:$A,_xlfn.CHOOSECOLS(netflixPart2!$A:$F,_xlfn.XMATCH(netflixPart1!G$1,netflixPart2!$A$1:$F$1))),"Missing"),1,1)} -> 42736 | H2936: {=IFERROR(_xlfn.XLOOKUP($A2936,netflixPart2!$A:$A,_xlfn.CHOOSECOLS(netflixPart2!$A:$F,_xlfn.XMATCH(netflixPart1!H$1,netflixPart2!$A$1:$F$1))),"Missing")} -> TV-MA | I2936: {=IFERROR(_xlfn.XLOOKUP($A2936,netflixPart2!$A:$A,_xlfn.CHOOSECOLS(netflixPart2!$A:$F,_xlfn.XMATCH(netflixPart1!I$1,netflixPart2!$A$1:$F$1))),"Missing")} -> 100 min | J2936: {=IFERROR(_xlfn.XLOOKUP($A2936,netflixPart2!$A:$A,_xlfn.CHOOSECOLS(netflixPart2!$A:$F,_xlfn.XMATCH(netflixPart1!J$1,netflixPart2!$A$1:$F$1))),"Missing")} -> Action & Adventure, Comedies, International Movies
A2937: s3983 | B2937: Movie | C2937: Mirage | D2937: Oriol Paulo | E2937: Spain | F2937: {=IFERROR(_xlfn.XLOOKUP($A2937,netflixPart2!$A:$A,_xlfn.CHOOSECOLS(netflixPart2!$A:$F,_xlfn.XMATCH(netflixPart1!F$1,netflixPart2!$A$1:$F$1))),"Missing")} -> 3/22/2019 | G2937: {=DATE(IFERROR(_xlfn.XLOOKUP($A2937,netflixPart2!$A:$A,_xlfn.CHOOSECOLS(netflixPart2!$A:$F,_xlfn.XMATCH(netflixPart1!G$1,netflixPart2!$A$1:$F$1))),"Missing"),1,1)} -> 43101 | H2937: {=IFERROR(_xlfn.XLOOKUP($A2937,netflixPart2!$A:$A,_xlfn.CHOOSECOLS(netflixPart2!$A:$F,_xlfn.XMATCH(netflixPart1!H$1,netflixPart2!$A$1:$F$1))),"Missing")} -> TV-MA | I2937: {=IFERROR(_xlfn.XLOOKUP($A2937,netflixPart2!$A:$A,_xlfn.CHOOSECOLS(netflixPart2!$A:$F,_xlfn.XMATCH(netflixPart1!I$1,netflixPart2!$A$1:$F$1))),"Missing")} -> 129 min | J2937: {=IFERROR(_xlfn.XLOOKUP($A2937,netflixPart2!$A:$A,_xlfn.CHOOSECOLS(netflixPart2!$A:$F,_xlfn.XMATCH(netflixPart1!J$1,netflixPart2!$A$1:$F$1))),"Missing")} -> Dramas, International Movies, Sci-Fi & Fantasy
A2938: s3984 | B2938: Movie | C2938: ReMastered: The Miami Showband Massacre | D2938: Stuart Sender | E2938: United States | F2938: {=IFERROR(_xlfn.XLOOKUP($A2938,netflixPart2!$A:$A,_xlfn.CHOOSECOLS(netflixPart2!$A:$F,_xlfn.XMATCH(netflixPart1!F$1,netflixPart2!$A$1:$F$1))),"Missing")} -> 3/22/2019 | G2938: {=DATE(IFERROR(_xlfn.XLOOKUP($A2938,netflixPart2!$A:$A,_xlfn.CHOOSECOLS(netflixPart2!$A:$F,_xlfn.XMATCH(netflixPart1!G$1,netflixPart2!$A$1:$F$1))),"Missing"),1,1)} -> 43466 | H2938: {=IFERROR(_xlfn.XLOOKUP($A2938,netflixPart2!$A:$A,_xlfn.CHOOSECOLS(netflixPart2!$A:$F,_xlfn.XMATCH(netflixPart1!H$1,netflixPart2!$A$1:$F$1))),"Missing")} -> TV-MA | I2938: {=IFERROR(_xlfn.XLOOKUP($A2938,netflixPart2!$A:$A,_xlfn.CHOOSECOLS(netflixPart2!$A:$F,_xlfn.XMATCH(netflixPart1!I$1,netflixPart2!$A$1:$F$1))),"Missing")} -> 71 min | J2938: {=IFERROR(_xlfn.XLOOKUP($A2938,netflixPart2!$A:$A,_xlfn.CHOOSECOLS(netflixPart2!$A:$F,_xlfn.XMATCH(netflixPart1!J$1,netflixPart2!$A$1:$F$1))),"Missing")} -> Documentaries, Music & Musicals
A2939: s3986 | B2939: Movie | C2939: The Dirt | D2939: Jeff Tremaine | E2939: United States | F2939: {=IFERROR(_xlfn.XLOOKUP($A2939,netflixPart2!$A:$A,_xlfn.CHOOSECOLS(netflixPart2!$A:$F,_xlfn.XMATCH(netflixPart1!F$1,netflixPart2!$A$1:$F$1))),"Missing")} -> 3/22/2019 | G2939: {=DATE(IFERROR(_xlfn.XLOOKUP($A2939,netflixPart2!$A:$A,_xlfn.CHOOSECOLS(netflixPart2!$A:$F,_xlfn.XMATCH(netflixPart1!G$1,netflixPart2!$A$1:$F$1))),"Missing"),1,1)} -> 43466 | H2939: {=IFERROR(_xlfn.XLOOKUP($A2939,netflixPart2!$A:$A,_xlfn.CHOOSECOLS(netflixPart2!$A:$F,_xlfn.XMATCH(netflixPart1!H$1,netflixPart2!$A$1:$F$1))),"Missing")} -> TV-MA | I2939: {=IFERROR(_xlfn.XLOOKUP($A2939,netflixPart2!$A:$A,_xlfn.CHOOSECOLS(netflixPart2!$A:$F,_xlfn.XMATCH(netflixPart1!I$1,netflixPart2!$A$1:$F$1))),"Missing")} -> 108 min | J2939: {=IFERROR(_xlfn.XLOOKUP($A2939,netflixPart2!$A:$A,_xlfn.CHOOSECOLS(netflixPart2!$A:$F,_xlfn.XMATCH(netflixPart1!J$1,netflixPart2!$A$1:$F$1))),"Missing")} -> Comedies, Dramas, Music & Musicals
... A3286: s4520 | B3286: Movie | C3286: The Kindergarten Teacher | D3286: Sara Colangelo | E3286: United States | F3286: {=IFERROR(_xlfn.XLOOKUP($A3286,netflixPart2!$A:$A,_xlfn.CHOOSECOLS(netflixPart2!$A:$F,_xlfn.XMATCH(netflixPart1!F$1,netflixPart2!$A$1:$F$1))),"Missing")} -> 10/12/2018 | G3286: {=DATE(IFERROR(_xlfn.XLOOKUP($A3286,netflixPart2!$A:$A,_xlfn.CHOOSECOLS(netflixPart2!$A:$F,_xlfn.XMATCH(netflixPart1!G$1,netflixPart2!$A$1:$F$1))),"Missing"),1,1)} -> 43101 | H3286: {=IFERROR(_xlfn.XLOOKUP($A3286,netflixPart2!$A:$A,_xlfn.CHOOSECOLS(netflixPart2!$A:$F,_xlfn.XMATCH(netflixPart1!H$1,netflixPart2!$A$1:$F$1))),"Missing")} -> R | I3286: {=IFERROR(_xlfn.XLOOKUP($A3286,netflixPart2!$A:$A,_xlfn.CHOOSECOLS(netflixPart2!$A:$F,_xlfn.XMATCH(netflixPart1!I$1,netflixPart2!$A$1:$F$1))),"Missing")} -> 97 min | J3286: {=IFERROR(_xlfn.XLOOKUP($A3286,netflixPart2!$A:$A,_xlfn.CHOOSECOLS(netflixPart2!$A:$F,_xlfn.XMATCH(netflixPart1!J$1,netflixPart2!$A$1:$F$1))),"Missing")} -> Dramas, Independent Movies
A3287: s4523 | B3287: Movie | C3287: 22-Jul | D3287: Paul Greengrass | E3287: Norway | F3287: {=IFERROR(_xlfn.XLOOKUP($A3287,netflixPart2!$A:$A,_xlfn.CHOOSECOLS(netflixPart2!$A:$F,_xlfn.XMATCH(netflixPart1!F$1,netflixPart2!$A$1:$F$1))),"Missing")} -> 10/10/2018 | G3287: {=DATE(IFERROR(_xlfn.XLOOKUP($A3287,netflixPart2!$A:$A,_xlfn.CHOOSECOLS(netflixPart2!$A:$F,_xlfn.XMATCH(netflixPart1!G$1,netflixPart2!$A$1:$F$1))),"Missing"),1,1)} -> 43101 | H3287: {=IFERROR(_xlfn.XLOOKUP($A3287,netflixPart2!$A:$A,_xlfn.CHOOSECOLS(netflixPart2!$A:$F,_xlfn.XMATCH(netflixPart1!H$1,netflixPart2!$A$1:$F$1))),"Missing")} -> R | I3287: {=IFERROR(_xlfn.XLOOKUP($A3287,netflixPart2!$A:$A,_xlfn.CHOOSECOLS(netflixPart2!$A:$F,_xlfn.XMATCH(netflixPart1!I$1,netflixPart2!$A$1:$F$1))),"Missing")} -> 144 min | J3287: {=IFERROR(_xlfn.XLOOKUP($A3287,netflixPart2!$A:$A,_xlfn.CHOOSECOLS(netflixPart2!$A:$F,_xlfn.XMATCH(netflixPart1!J$1,netflixPart2!$A$1:$F$1))),"Missing")} -> Dramas, Thrillers | K3287: =_xlfn.TEXTJOIN("|",FALSE,B3287:J3287) -> Movie|22-Jul|Paul Greengrass|Norway|10/10/2018|43101|R|144 min|Dramas, Thrillers
A3288: s4525 | B3288: Movie | C3288: Tales From the Hood 2 | D3288: Rusty Cundieff, Darin Scott | E3288: United States | F3288: {=IFERROR(_xlfn.XLOOKUP($A3288,netflixPart2!$A:$A,_xlfn.CHOOSECOLS(netflixPart2!$A:$F,_xlfn.XMATCH(netflixPart1!F$1,netflixPart2!$A$1:$F$1))),"Missing")} -> 10/10/2018 | G3288: {=DATE(IFERROR(_xlfn.XLOOKUP($A3288,netflixPart2!$A:$A,_xlfn.CHOOSECOLS(netflixPart2!$A:$F,_xlfn.XMATCH(netflixPart1!G$1,netflixPart2!$A$1:$F$1))),"Missing"),1,1)} -> 43101 | H3288: {=IFERROR(_xlfn.XLOOKUP($A3288,netflixPart2!$A:$A,_xlfn.CHOOSECOLS(netflixPart2!$A:$F,_xlfn.XMATCH(netflixPart1!H$1,netflixPart2!$A$1:$F$1))),"Missing")} -> R | I3288: {=IFERROR(_xlfn.XLOOKUP($A3288,netflixPart2!$A:$A,_xlfn.CHOOSECOLS(netflixPart2!$A:$F,_xlfn.XMATCH(netflixPart1!I$1,netflixPart2!$A$1:$F$1))),"Missing")} -> 110 min | J3288: {=IFERROR(_xlfn.XLOOKUP($A3288,netflixPart2!$A:$A,_xlfn.CHOOSECOLS(netflixPart2!$A:$F,_xlfn.XMATCH(netflixPart1!J$1,netflixPart2!$A$1:$F$1))),"Missing")} -> Cult Movies, Horror Movies, Independent Movies
...

Sheet draft- duplications
A1: show_id | B1: type | C1: title | D1: director | E1: country | F1: date_added | G1: release_year | H1: rating | I1: duration | J1: listed_in | K1: duplication
A2: s160 | B2: Movie | C2: Love in a Puff | D2: Pang Ho-cheung | E2: Hong Kong | F2: 09/01/2021 | G2: 40179 | H2: TV-MA | I2: 103 min | J2: Comedies, Dramas, International Movies | K2: Movie|Love in a Puff|Pang Ho-cheung|Hong Kong|09/01/2021|40179|TV-MA|103 min|Comedies, Dramas, International Movies
A3: s3997 | B3: TV Show | C3: 09-Feb | D3: Not Given | E3: Pakistan | F3: 3/20/2019 | G3: 43101 | H3: TV-14 | I3: 1 Season | J3: International TV Shows, TV Dramas | K3: TV Show|09-Feb|Not Given|Pakistan|3/20/2019|43101|TV-14|1 Season|International TV Shows, TV Dramas
A4: s304 | B4: Movie | C4: Esperando la carroza | D4: Alejandro Doria | E4: Argentina | F4: 08/05/2021 | G4: 31048 | H4: TV-MA | I4: 95 min | J4: Comedies, Cult Movies, International Movies | K4: Movie|Esperando la carroza|Alejandro Doria|Argentina|08/05/2021|31048|TV-MA|95 min|Comedies, Cult Movies, International Movies
A5: s5965 | B5: TV Show | C5: 09-Feb | D5: Not Given | E5: Pakistan | F5: 3/20/2019 | G5: 43101 | H5: TV-14 | I5: 1 Season | J5: International TV Shows, TV Dramas | K5: TV Show|09-Feb|Not Given|Pakistan|3/20/2019|43101|TV-14|1 Season|International TV Shows, TV Dramas
A6: s3963 | B6: Movie | C6: 15-Aug | D6: Swapnaneel Jayakar | E6: India | F6: 3/29/2019 | G6: 43466 | H6: TV-14 | I6: 124 min | J6: Comedies, Dramas, Independent Movies | K6: Movie|15-Aug|Swapnaneel Jayakar|India|3/29/2019|43466|TV-14|124 min|Comedies, Dramas, Independent Movies
A7: s4523 | B7: Movie | C7: 22-Jul | D7: Paul Greengrass | E7: Norway | F7: 10/10/2018 | G7: 43101 | H7: R | I7: 144 min | J7: Dramas, Thrillers | K7: Movie|22-Jul|Paul Greengrass|Norway|10/10/2018|43101|R|144 min|Dramas, Thrillers
A8: s5034 | B8: Movie | C8: FullMetal Alchemist | D8: Fumihiko Sori | E8: Japan | F8: 2/19/2018 | G8: 42736 | H8: TV-PG | I8: 134 min | J8: Action & Adventure, Dramas, International Movies | K8: Movie|FullMetal Alchemist|Fumihiko Sori|Japan|2/19/2018|42736|TV-PG|134 min|Action & Adventure, Dramas, International Movies
A9: s5319 | B9: Movie | C9: Death Note | D9: Adam Wingard | E9: United States | F9: 8/25/2017 | G9: 42736 | H9: TV-MA | I9: 100 min | J9: Horror Movies, Thrillers | K9: Movie|Death Note|Adam Wingard|United States|8/25/2017|42736|TV-MA|100 min|Horror Movies, Thrillers
A10: s5966 | B10: Movie | C10: 22-Jul | D10: Paul Greengrass | E10: Norway | F10: 10/10/2018 | G10: 43101 | H10: R | I10: 144 min | J10: Dramas, Thrillers | K10: Movie|22-Jul|Paul Greengrass|Norway|10/10/2018|43101|R|144 min|Dramas, Thrillers
A11: s5967 | B11: Movie | C11: 15-Aug | D11: Swapnaneel Jayakar | E11: India | F11: 3/29/2019 | G11: 43466 | H11: TV-14 | I11: 124 min | J11: Comedies, Dramas, Independent Movies | K11: Movie|15-Aug|Swapnaneel Jayakar|India|3/29/2019|43466|TV-14|124 min|Comedies, Dramas, Independent Movies
A12: s6706 | B12: Movie | C12: Esperando La Carroza | D12: Alejandro Doria | E12: Argentina | F12: 7/15/2018 | G12: 31048 | H12: NR | I12: 95 min | J12: Comedies, Cult Movies, International Movies | K12: Movie|Esperando La Carroza|Alejandro Doria|Argentina|7/15/2018|31048|NR|95 min|Comedies, Cult Movies, International Movies
A13: s7346 | B13: Movie | C13: Love In A Puff | D13: Pang Ho-cheung | E13: Hong Kong | F13: 08/01/2018 | G13: 40179 | H13: TV-MA | I13: 103 min | J13: Comedies, Dramas, International Movies | K13: Movie|Love In A Puff|Pang Ho-cheung|Hong Kong|08/01/2018|40179|TV-MA|103 min|Comedies, Dramas, International Movies
... A17: s8023 | B17: TV Show | C17: Sin Senos sí Hay Paraíso | D17: Not Given | E17: United States | F17: 01/11/2019 | G17: 43101 | H17: TV-MA | I17: 3 Seasons | J17: International TV Shows, Spanish-Language TV Shows, TV Dramas | K17: TV Show|Sin Senos sí Hay Paraíso|Not Given|United States|01/11/2019|43101|TV-MA|3 Seasons|International TV Shows, Spanish-Language TV Shows, TV Dramas
